DO_AN/DO_AN.srcs/sources_1/new/apb_uart_slave.v
module apb_uart_slave #(
    parameter CLK_FREQ  = 50000000, // Tần số PCLK mặc định là 50MHz
    parameter BAUD_RATE = 115200
)(
    input  wire        PCLK, PRESETn,
    input  wire [31:0] UART_PADDR,
    input  wire        UART_PSEL, UART_PENABLE, UART_PWRITE,
    input  wire [31:0] UART_PWDATA,
    output reg  [31:0] UART_PRDATA,
    output wire        UART_PREADY,
    // Chân FPGA
    output wire        uart_tx,
    input  wire        uart_rx
);
    // Định nghĩa các thanh ghi nội bộ
    reg [7:0] tx_data;
    reg       tx_start;
    wire      tx_busy;
    wire [7:0] rx_data;
    wire       rx_ready;
    reg        rx_clear;

    // Bộ giải mã địa chỉ APB (Write)
    wire tx_write = UART_PSEL && UART_PENABLE && UART_PWRITE &&
                    (UART_PADDR[7:0] == 8'h00);
    assign UART_PREADY = !(tx_write && tx_busy);

    wire apb_write = UART_PSEL && UART_PENABLE && UART_PWRITE && UART_PREADY;
    always @(posedge PCLK or negedge PRESETn) begin
        if (!PRESETn) begin
            tx_data  <= 8'h0;
            tx_start <= 1'b0;
        end else begin
            tx_start <= 1'b0;
            if (apb_write && (UART_PADDR[7:0] == 8'h00)) begin
                tx_data  <= UART_PWDATA[7:0];
                tx_start <= 1'b1;
            end
        end
    end

    // Bộ giải mã địa chỉ APB (Read)
    wire apb_read = UART_PSEL && !UART_PWRITE;
    always @(*) begin
        rx_clear = 1'b0;
        if (apb_read) begin
            case (UART_PADDR[7:0])
                8'h04: begin
                    UART_PRDATA   = {24'b0, rx_data};
                    rx_clear = UART_PENABLE; // Xóa cờ báo dữ liệu sau khi đọc xong
                end
                8'h08:   UART_PRDATA = {30'b0, rx_ready, !tx_busy};
                default: UART_PRDATA = 32'h0;
            endcase
        end else begin
            UART_PRDATA = 32'h0;
        end
    end

    // ─── LÕI UART TX (PHÁT TÍN HIỆU) ───
    localparam BIT_PERIOD = CLK_FREQ / BAUD_RATE;
    reg [15:0] clk_cnt;
    reg [3:0]  bit_idx;
    reg [9:0]  tx_shift_reg;
    reg        tx_active;

    assign uart_tx = tx_active ? tx_shift_reg[0] : 1'b1;
    assign tx_busy = tx_active || tx_start;

    always @(posedge PCLK or negedge PRESETn) begin
        if (!PRESETn) begin
            clk_cnt <= 0; bit_idx <= 0; tx_active <= 0; tx_shift_reg <= 10'b1;
        end else if (tx_start && !tx_active) begin
            tx_active    <= 1'b1;
            tx_shift_reg <= {1'b1, tx_data, 1'b0}; // [Stop bit (1), Data (8-bit), Start bit (0)]
            clk_cnt      <= 0; bit_idx <= 0;
        end else if (tx_active) begin
            if (clk_cnt < BIT_PERIOD - 1) begin
                clk_cnt <= clk_cnt + 1;
            end else begin
                clk_cnt <= 0;
                if (bit_idx < 9) begin
                    bit_idx      <= bit_idx + 1;
                    tx_shift_reg <= tx_shift_reg >> 1;
                end else begin
                    tx_active <= 1'b0;
                end
            end
        end
    end

    // ─── LÕI UART RX (NHẬN TÍN HIỆU) ───
    // Tự động lấy mẫu ở giữa chu kỳ bit để tránh nhiễu tín hiệu
    reg [1:0] rx_sync;
    always @(posedge PCLK) rx_sync <= {rx_sync[0], uart_rx}; // Chống hiện tượng bất ổn định (Metastability)

    reg        rx_active;
    reg [15:0] rx_clk_cnt;
    reg [3:0]  rx_bit_idx;
    reg [7:0]  rx_shift_data;
    reg        rx_done;

    assign rx_data  = rx_shift_data;
    assign rx_ready = rx_done;

    always @(posedge PCLK or negedge PRESETn) begin
        if (!PRESETn) begin
            rx_active <= 0; rx_clk_cnt <= 0; rx_bit_idx <= 0; rx_done <= 0;
        end else begin
            if (rx_clear) rx_done <= 1'b0;
            
            if (!rx_active && (rx_sync[1] == 1'b0)) begin // Phát hiện Start bit
                rx_active  <= 1'b1;
                rx_clk_cnt <= 0;
                rx_bit_idx <= 0;
            end else if (rx_active) begin
                if (rx_clk_cnt < BIT_PERIOD - 1) begin
                    rx_clk_cnt <= rx_clk_cnt + 1;
                end else begin
                    rx_clk_cnt <= 0;
                    if (rx_bit_idx == 0) begin // Bỏ qua Start bit
                        rx_bit_idx <= rx_bit_idx + 1;
                    end else if (rx_bit_idx <= 8) begin
                        rx_shift_data <= {rx_sync[1], rx_shift_data[7:1]};
                        rx_bit_idx    <= rx_bit_idx + 1;
                    end else begin
                        rx_active <= 1'b0;
                        rx_done   <= 1'b1; // Đã nhận đủ 1 khung byte dữ liệu
                    end
                end
            end
        end
    end
endmodule

DO_AN/DO_AN.srcs/sim_1/new/tb_apb_uart_slave_unit.v
`timescale 1ns / 1ps
`default_nettype none

module tb_apb_uart_slave_unit;
   reg clk = 1'b0;
   reg presetn = 1'b0;

   reg  [31:0] UART_PADDR = 32'h00000000;
   reg         UART_PSEL = 1'b0;
   reg         UART_PENABLE = 1'b0;
   reg         UART_PWRITE = 1'b0;
   reg  [31:0] UART_PWDATA = 32'h00000000;
   wire [31:0] UART_PRDATA;
   wire        UART_PREADY;
   wire        uart_tx;
   reg         uart_rx = 1'b1;

   reg [9:0] sampled_frame;

   always #5 clk = ~clk;

   apb_uart_slave #(
      .CLK_FREQ(20),
      .BAUD_RATE(10)
   ) dut (
      .PCLK(clk),
      .PRESETn(presetn),
      .UART_PADDR(UART_PADDR),
      .UART_PSEL(UART_PSEL),
      .UART_PENABLE(UART_PENABLE),
      .UART_PWRITE(UART_PWRITE),
      .UART_PWDATA(UART_PWDATA),
      .UART_PRDATA(UART_PRDATA),
      .UART_PREADY(UART_PREADY),
      .uart_tx(uart_tx),
      .uart_rx(uart_rx)
   );

   task fail;
      input [127:0] message;
      begin
         $display("FAIL: %0s", message);
         $finish;
      end
   endtask

   task apb_write;
      input [7:0] addr;
      input [7:0] data;
      begin
         @(negedge clk);
         UART_PADDR   <= {24'h0, addr};
         UART_PWDATA  <= {24'h0, data};
         UART_PWRITE  <= 1'b1;
         UART_PSEL    <= 1'b1;
         UART_PENABLE <= 1'b0;
         @(posedge clk);
         #1;
         UART_PENABLE <= 1'b1;
         while (!UART_PREADY) begin
            @(posedge clk);
            #1;
         end
         @(posedge clk);
         #1;
         UART_PSEL    <= 1'b0;
         UART_PENABLE <= 1'b0;
         UART_PWRITE  <= 1'b0;
         UART_PADDR   <= 32'h00000000;
         UART_PWDATA  <= 32'h00000000;
      end
   endtask

   task apb_read;
      input [7:0] addr;
      output [31:0] data;
      begin
         @(negedge clk);
         UART_PADDR   <= {24'h0, addr};
         UART_PWRITE  <= 1'b0;
         UART_PSEL    <= 1'b1;
         UART_PENABLE <= 1'b0;
         @(posedge clk);
         #1;
         UART_PENABLE <= 1'b1;
         while (!UART_PREADY) begin
            @(posedge clk);
            #1;
         end
         data = UART_PRDATA;
         @(posedge clk);
         #1;
         UART_PSEL    <= 1'b0;
         UART_PENABLE <= 1'b0;
         UART_PADDR   <= 32'h00000000;
      end
   endtask

   task drive_uart_rx_byte;
      input [7:0] value;
      integer bit_idx;
      begin
         uart_rx <= 1'b0;
         repeat (2) @(posedge clk);
         for (bit_idx = 0; bit_idx < 8; bit_idx = bit_idx + 1) begin
            uart_rx <= value[bit_idx];
            repeat (2) @(posedge clk);
         end
         uart_rx <= 1'b1;
         repeat (2) @(posedge clk);
      end
   endtask

   task sample_tx_frame;
      input [7:0] expected_byte;
      integer bit_idx;
      begin
         sampled_frame = 10'b0;
         @(posedge clk);
         #1;
         sampled_frame[0] = uart_tx;
         for (bit_idx = 0; bit_idx < 9; bit_idx = bit_idx + 1) begin
            repeat (2) @(posedge clk);
            #1;
            sampled_frame[bit_idx + 1] = uart_tx;
         end
         if (sampled_frame[0] !== 1'b0) fail("UART TX start bit must be low");
         if (sampled_frame[9] !== 1'b1) fail("UART TX stop bit must be high");
         if (sampled_frame[1] !== expected_byte[0]) fail("UART TX bit 0 mismatch");
         if (sampled_frame[2] !== expected_byte[1]) fail("UART TX bit 1 mismatch");
         if (sampled_frame[3] !== expected_byte[2]) fail("UART TX bit 2 mismatch");
         if (sampled_frame[4] !== expected_byte[3]) fail("UART TX bit 3 mismatch");
         if (sampled_frame[5] !== expected_byte[4]) fail("UART TX bit 4 mismatch");
         if (sampled_frame[6] !== expected_byte[5]) fail("UART TX bit 5 mismatch");
         if (sampled_frame[7] !== expected_byte[6]) fail("UART TX bit 6 mismatch");
         if (sampled_frame[8] !== expected_byte[7]) fail("UART TX bit 7 mismatch");
      end
   endtask

   task wait_for_rx_ready;
      output [31:0] status;
      integer n;
      begin
         for (n = 0; n < 40; n = n + 1) begin
            apb_read(8'h08, status);
            if (status[1] === 1'b1) begin
               disable wait_for_rx_ready;
            end
            repeat (2) @(posedge clk);
         end
         fail("UART rx_ready did not assert in time");
      end
   endtask

   initial begin
      $dumpfile("tb_apb_uart_slave_unit.vcd");
      $dumpvars(0, tb_apb_uart_slave_unit);

      repeat (4) @(posedge clk);
      presetn <= 1'b1;
      repeat (2) @(posedge clk);

      if (uart_tx !== 1'b1) fail("UART TX must idle high after reset");

      $display("UART TX check: start");

      apb_write(8'h00, 8'hA5);
      sample_tx_frame(8'hA5);
      $display("UART TX check: PASS");

      $display("UART RX check: drive byte 0xFF on uart_rx");
      drive_uart_rx_byte(8'hFF);

      begin : status_check
         reg [31:0] status;
         wait_for_rx_ready(status);
         if (status[1:0] !== 2'b11) fail("UART status should show rx_ready=1 and tx_idle=1");
         $display("UART RX ready check: PASS");
      end

      begin : rx_read_check
         reg [31:0] rx_data;
         apb_read(8'h04, rx_data);
         if (rx_data[7:0] !== 8'hFF) fail("UART RX data mismatch");
         $display("UART RX data check: PASS (0x%02h)", rx_data[7:0]);
      end

      begin : status_clear_check
         reg [31:0] status_after;
         apb_read(8'h08, status_after);
         if (status_after[1:0] !== 2'b01) fail("UART rx_ready should clear after data read");
         $display("UART RX clear check: PASS");
      end

      $display("PASS: apb_uart_slave self-check completed");
      $finish;
   end
endmodule

`default_nettype wire

tb_apb_uart_slave_unit.vcd
$date
	Fri Jul 24 15:54:45 2026
$end
$version
	Icarus Verilog
$end
$timescale
	1ps
$end
$scope module tb_apb_uart_slave_unit $end
$var wire 1 ! uart_tx $end
$var wire 1 " UART_PREADY $end
$var wire 32 # UART_PRDATA [31:0] $end
$var reg 32 $ UART_PADDR [31:0] $end
$var reg 1 % UART_PENABLE $end
$var reg 1 & UART_PSEL $end
$var reg 32 ' UART_PWDATA [31:0] $end
$var reg 1 ( UART_PWRITE $end
$var reg 1 ) clk $end
$var reg 1 * presetn $end
$var reg 10 + sampled_frame [9:0] $end
$var reg 1 , uart_rx $end
$scope module dut $end
$var wire 1 ) PCLK $end
$var wire 1 * PRESETn $end
$var wire 32 - UART_PADDR [31:0] $end
$var wire 1 % UART_PENABLE $end
$var wire 1 & UART_PSEL $end
$var wire 32 . UART_PWDATA [31:0] $end
$var wire 1 ( UART_PWRITE $end
$var wire 1 / apb_read $end
$var wire 1 0 apb_write $end
$var wire 8 1 rx_data [7:0] $end
$var wire 1 2 rx_ready $end
$var wire 1 3 tx_busy $end
$var wire 1 4 tx_write $end
$var wire 1 , uart_rx $end
$var wire 1 ! uart_tx $end
$var wire 1 " UART_PREADY $end
$var parameter 32 5 BAUD_RATE $end
$var parameter 32 6 BIT_PERIOD $end
$var parameter 32 7 CLK_FREQ $end
$var reg 32 8 UART_PRDATA [31:0] $end
$var reg 4 9 bit_idx [3:0] $end
$var reg 16 : clk_cnt [15:0] $end
$var reg 1 ; rx_active $end
$var reg 4 < rx_bit_idx [3:0] $end
$var reg 1 = rx_clear $end
$var reg 16 > rx_clk_cnt [15:0] $end
$var reg 1 ? rx_done $end
$var reg 8 @ rx_shift_data [7:0] $end
$var reg 2 A rx_sync [1:0] $end
$var reg 1 B tx_active $end
$var reg 8 C tx_data [7:0] $end
$var reg 10 D tx_shift_reg [9:0] $end
$var reg 1 E tx_start $end
$upscope $end
$scope begin rx_read_check $end
$var reg 32 F rx_data [31:0] $end
$upscope $end
$scope begin status_check $end
$var reg 32 G status [31:0] $end
$upscope $end
$scope begin status_clear_check $end
$var reg 32 H status_after [31:0] $end
$upscope $end
$scope task apb_read $end
$var reg 8 I addr [7:0] $end
$var reg 32 J data [31:0] $end
$upscope $end
$scope task apb_write $end
$var reg 8 K addr [7:0] $end
$var reg 8 L data [7:0] $end
$upscope $end
$scope task drive_uart_rx_byte $end
$var reg 8 M value [7:0] $end
$var integer 32 N bit_idx [31:0] $end
$upscope $end
$scope task fail $end
$var reg 128 O message [127:0] $end
$upscope $end
$scope task sample_tx_frame $end
$var reg 8 P expected_byte [7:0] $end
$var integer 32 Q bit_idx [31:0] $end
$upscope $end
$scope task wait_for_rx_ready $end
$var reg 32 R status [31:0] $end
$var integer 32 S n [31:0] $end
$upscope $end
$upscope $end
$enddefinitions $end
$comment Show the parameter values. $end
$dumpall
b10100 7
b10 6
b1010 5
$end
#0
$dumpvars
bx S
bx R
bx Q
bx P
bx O
bx N
bx M
bx L
bx K
bx J
bx I
bx H
bx G
bx F
xE
bx D
bx C
xB
bx A
bx @
x?
bx >
x=
bx <
x;
bx :
bx 9
bx 8
04
x3
x2
bx 1
00
0/
b0 .
b0 -
1,
bx +
0*
0)
0(
b0 '
0&
0%
b0 $
bx #
1"
x!
$end
#5000
1!
03
b0 #
b0 8
0=
0E
b0 C
b1 D
0B
b0 9
b0 :
02
0?
b0 <
b0 >
0;
bx1 A
1)
#10000
0)
#15000
b11 A
1)
#20000
0)
#25000
1)
#30000
0)
#35000
1*
1)
#40000
0)
#45000
1)
#50000
0)
#55000
b10100101 L
b0 K
1)
#60000
1&
1(
b10100101 '
b10100101 .
0)
#65000
1)
#66000
14
10
1%
#70000
0)
#75000
00
0"
13
1E
b10100101 C
1)
#76000
1"
04
b0 '
b0 .
0(
0%
0&
b0 +
b10100101 P
#80000
0)
#85000
0!
0E
b1101001010 D
1B
1)
#86000
b0 Q
#90000
0)
#95000
b1 :
1)
#100000
0)
#105000
1!
b110100101 D
b1 9
b0 :
1)
#106000
b1 Q
b10 +
#110000
0)
#115000
b1 :
1)
#120000
0)
#125000
0!
b11010010 D
b10 9
b0 :
1)
#126000
b10 Q
#130000
0)
#135000
b1 :
1)
#140000
0)
#145000
1!
b1101001 D
b11 9
b0 :
1)
#146000
b11 Q
b1010 +
#150000
0)
#155000
b1 :
1)
#160000
0)
#165000
0!
b110100 D
b100 9
b0 :
1)
#166000
b100 Q
#170000
0)
#175000
b1 :
1)
#180000
0)
#185000
b11010 D
b101 9
b0 :
1)
#186000
b101 Q
#190000
0)
#195000
b1 :
1)
#200000
0)
#205000
1!
b1101 D
b110 9
b0 :
1)
#206000
b110 Q
b1001010 +
#210000
0)
#215000
b1 :
1)
#220000
0)
#225000
0!
b110 D
b111 9
b0 :
1)
#226000
b111 Q
#230000
0)
#235000
b1 :
1)
#240000
0)
#245000
1!
b11 D
b1000 9
b0 :
1)
#246000
b1000 Q
b101001010 +
#250000
0)
#255000
b1 :
1)
#260000
0)
#265000
b1 D
b1001 9
b0 :
1)
#266000
0,
b11111111 M
b1001 Q
b1101001010 +
#270000
0)
#275000
b1 :
b10 A
1)
#280000
0)
#285000
03
0B
b0 :
1,
b0 A
b0 N
1)
#290000
0)
#295000
1;
b1 A
1)
#300000
0)
#305000
b1 >
b11 A
b1 N
1)
#310000
0)
#315000
b1 <
b0 >
1)
#320000
0)
#325000
b1 >
b10 N
1)
#330000
0)
#335000
b10 <
b1xxxxxxx 1
b1xxxxxxx @
b0 >
1)
#340000
0)
#345000
b1 >
b11 N
1)
#350000
0)
#355000
b11 <
b11xxxxxx 1
b11xxxxxx @
b0 >
1)
#360000
0)
#365000
b1 >
b100 N
1)
#370000
0)
#375000
b100 <
b111xxxxx 1
b111xxxxx @
b0 >
1)
#380000
0)
#385000
b1 >
b101 N
1)
#390000
0)
#395000
b101 <
b1111xxxx 1
b1111xxxx @
b0 >
1)
#400000
0)
#405000
b1 >
b110 N
1)
#410000
0)
#415000
b110 <
b11111xxx 1
b11111xxx @
b0 >
1)
#420000
0)
#425000
b1 >
b111 N
1)
#430000
0)
#435000
b111 <
b111111xx 1
b111111xx @
b0 >
1)
#440000
0)
#445000
b1 >
b1000 N
1)
#450000
0)
#455000
b1000 <
b1111111x 1
b1111111x @
b0 >
1)
#460000
0)
#465000
b1 >
b1000 I
b0 S
1)
#470000
b1 #
b1 8
1/
1&
b1000 $
b1000 -
0)
#475000
b1001 <
b11111111 1
b11111111 @
b0 >
1)
#476000
1%
b1 J
#480000
0)
#485000
b1 >
1)
#486000
b0 #
b0 8
0/
b0 $
b0 -
0%
0&
b1 R
#490000
0)
#495000
12
1?
0;
b0 >
1)
#500000
0)
#505000
b1 S
1)
#510000
b11 #
b11 8
1/
1&
b1000 $
b1000 -
0)
#515000
1)
#516000
1%
b11 J
#520000
0)
#525000
1)
#526000
b0 #
b0 8
0/
b0 $
b0 -
0%
0&
b100 I
b11 G
b11 R
#530000
b11111111 #
b11111111 8
1/
1&
b100 $
b100 -
0)
#535000
1)
#536000
1=
1%
b11111111 J
#540000
0)
#545000
1=
02
0?
1)
#546000
b0 #
b0 8
0=
0/
b0 $
b0 -
0%
0&
b1000 I
b11111111 F
#550000
b1 #
b1 8
1/
1&
b1000 $
b1000 -
0)
#555000
1)
#556000
1%
b1 J
#560000
0)
#565000
1)
#566000
b0 #
b0 8
0/
b0 $
b0 -
0%
0&
b1 H
