DO_AN/DO_AN.srcs/sources_1/new/apb_bridge.v
// ============================================================
//  FemtoRV32 Quark memory bus to APB bridge
//
//  Quark bus:
//    mem_rstrb pulses for instruction/data reads.
//    mem_wmask is non-zero for stores.
//    mem_rbusy / mem_wbusy hold the CPU in WAIT until APB completes.
//
//  APB sequence:
//    IDLE -> SETUP(PSEL=1,PENABLE=0)
//         -> ENABLE(PSEL=1,PENABLE=1, wait PREADY)
//         -> IDLE
// ============================================================

`default_nettype none

module apb_bridge (
    input  wire        clk,
    input  wire        resetn,

    input  wire        bus_sel,
    input  wire [31:0] mem_addr,
    input  wire [31:0] mem_wdata,
    input  wire [ 3:0] mem_wmask,
    input  wire        mem_rstrb,
    output reg  [31:0] mem_rdata,
    output wire        mem_rbusy,
    output wire        mem_wbusy,

    output reg  [31:0] PADDR,
    output reg         PWRITE,
    output reg         PSEL,
    output reg         PENABLE,
    output reg  [31:0] PWDATA,
    input  wire [31:0] PRDATA,
    input  wire        PREADY,
    input  wire        PSLVERR
);

    localparam S_IDLE   = 2'd0;
    localparam S_SETUP  = 2'd1;
    localparam S_ENABLE = 2'd2;

    reg [1:0] state;
    reg       txn_read;
    reg       txn_write;

    wire read_req  = bus_sel && mem_rstrb;
    wire write_req = bus_sel && |mem_wmask;
    wire request   = (read_req || write_req) && (state == S_IDLE);

    assign mem_rbusy = read_req ||
                       (((state == S_SETUP) || (state == S_ENABLE)) && txn_read);

    assign mem_wbusy = write_req ||
                       (((state == S_SETUP) || (state == S_ENABLE)) && txn_write);

    wire unused_pslverr = PSLVERR;

    always @(posedge clk or negedge resetn) begin
        if (!resetn) begin
            state     <= S_IDLE;
            txn_read  <= 1'b0;
            txn_write <= 1'b0;
            mem_rdata <= 32'h00000000;
            PADDR     <= 32'h00000000;
            PWRITE    <= 1'b0;
            PSEL      <= 1'b0;
            PENABLE   <= 1'b0;
            PWDATA    <= 32'h00000000;
        end else begin
            case (state)
                S_IDLE: begin
                    PSEL    <= 1'b0;
                    PENABLE <= 1'b0;

                    if (request) begin
                        PADDR     <= mem_addr;
                        PWRITE    <= write_req;
                        PWDATA    <= mem_wdata;
                        PSEL      <= 1'b1;
                        PENABLE   <= 1'b0;
                        txn_read  <= read_req;
                        txn_write <= write_req;
                        state     <= S_SETUP;
                    end
                end

                S_SETUP: begin
                    PSEL    <= 1'b1;
                    PENABLE <= 1'b1;
                    state   <= S_ENABLE;
                end

                S_ENABLE: begin
                    PSEL    <= 1'b1;
                    PENABLE <= 1'b1;

                    if (PREADY) begin
                        if (!PWRITE) begin
                            mem_rdata <= PRDATA;
                        end
                        PSEL      <= 1'b0;
                        PENABLE   <= 1'b0;
                        txn_read  <= 1'b0;
                        txn_write <= 1'b0;
                        state     <= S_IDLE;
                    end
                end

                default: begin
                    state <= S_IDLE;
                end
            endcase
        end
    end
endmodule

`default_nettype wire

DO_AN/DO_AN.srcs/sim_1/new/tb_apb_bridge_unit.v
`timescale 1ns / 1ps
`default_nettype none

module tb_apb_bridge_unit;
   reg clk = 1'b0;
   reg resetn = 1'b0;

   reg        bus_sel = 1'b0;
   reg [31:0] mem_addr = 32'h00000000;
   reg [31:0] mem_wdata = 32'h00000000;
   reg [3:0]  mem_wmask = 4'b0000;
   reg        mem_rstrb = 1'b0;
   wire [31:0] mem_rdata;
   wire        mem_rbusy;
   wire        mem_wbusy;

   wire [31:0] PADDR;
   wire        PWRITE;
   wire        PSEL;
   wire        PENABLE;
   wire [31:0] PWDATA;
   reg  [31:0] PRDATA = 32'h00000000;
   reg         PREADY = 1'b0;
   reg         PSLVERR = 1'b0;

   always #5 clk = ~clk;

   apb_bridge dut (
      .clk(clk),
      .resetn(resetn),
      .bus_sel(bus_sel),
      .mem_addr(mem_addr),
      .mem_wdata(mem_wdata),
      .mem_wmask(mem_wmask),
      .mem_rstrb(mem_rstrb),
      .mem_rdata(mem_rdata),
      .mem_rbusy(mem_rbusy),
      .mem_wbusy(mem_wbusy),
      .PADDR(PADDR),
      .PWRITE(PWRITE),
      .PSEL(PSEL),
      .PENABLE(PENABLE),
      .PWDATA(PWDATA),
      .PRDATA(PRDATA),
      .PREADY(PREADY),
      .PSLVERR(PSLVERR)
   );

   task fail;
      input [127:0] message;
      begin
         $display("FAIL: %0s", message);
         $finish;
      end
   endtask

   task tick;
      begin
         @(posedge clk);
         #1;
      end
   endtask

   task start_read;
      input [31:0] addr;
      begin
         @(negedge clk);
         bus_sel   <= 1'b1;
         mem_addr  <= addr;
         mem_wmask <= 4'b0000;
         mem_rstrb <= 1'b1;
         mem_wdata <= 32'h00000000;
      end
   endtask

   task start_write;
      input [31:0] addr;
      input [31:0] data;
      begin
         @(negedge clk);
         bus_sel   <= 1'b1;
         mem_addr  <= addr;
         mem_wdata <= data;
         mem_wmask <= 4'b1111;
         mem_rstrb <= 1'b0;
      end
   endtask

   initial begin
      $dumpfile("tb_apb_bridge_unit.vcd");
      $dumpvars(0, tb_apb_bridge_unit);

      repeat (2) tick();
      resetn <= 1'b1;
      tick();

      PRDATA <= 32'hcafebabe;
      PREADY <= 1'b0;
      start_read(32'h1234_5678);
      tick();
      if (!PSEL || PENABLE || PWRITE) fail("read did not enter SETUP correctly");
      if (PADDR !== 32'h1234_5678 || PWDATA !== 32'h00000000) fail("read address/data not latched");
      if (!mem_rbusy || mem_wbusy) fail("busy flags wrong in SETUP for read");

      mem_rstrb <= 1'b0;
      tick();
      if (!PSEL || !PENABLE || PWRITE) fail("read did not enter ENABLE correctly");
      if (!mem_rbusy) fail("read busy must stay high during ENABLE");

      tick();
      if (!PSEL || !PENABLE) fail("read must stall while PREADY is low");

      @(negedge clk);
      PREADY <= 1'b1;
      @(posedge clk);
      #1;
      if (mem_rdata !== 32'hcafebabe) fail("read data not captured on completion");
      if (PSEL || PENABLE) fail("APB bus not released after read completion");
      if (mem_rbusy || mem_wbusy) fail("busy flags not cleared after read completion");

      PREADY <= 1'b0;
      start_write(32'h0000_00a4, 32'hdead_beef);
      tick();
      if (!PSEL || PENABLE || !PWRITE) fail("write did not enter SETUP correctly");
      if (PADDR !== 32'h0000_00a4 || PWDATA !== 32'hdead_beef) fail("write payload not latched");
      if (!mem_wbusy || mem_rbusy) fail("busy flags wrong in SETUP for write");

      mem_wmask <= 4'b0000;
      tick();
      if (!PSEL || !PENABLE || !PWRITE) fail("write did not enter ENABLE correctly");
      if (!mem_wbusy) fail("write busy must stay high during ENABLE");

      tick();
      if (!PSEL || !PENABLE) fail("write must stall while PREADY is low");

      @(negedge clk);
      PREADY <= 1'b1;
      @(posedge clk);
      #1;
      if (PSEL || PENABLE) fail("APB bus not released after write completion");
      if (mem_rbusy || mem_wbusy) fail("busy flags not cleared after write completion");

      if (PSLVERR !== 1'b0) fail("PSLVERR should be tied low");

      $display("PASS: apb_bridge self-check completed");
      $finish;
   end
endmodule

`default_nettype wire

tb_apb_bridge_unit.vcd
$date
	Fri Jul 24 15:40:08 2026
$end
$version
	Icarus Verilog
$end
$timescale
	1ps
$end
$scope module tb_apb_bridge_unit $end
$var wire 1 ! mem_wbusy $end
$var wire 32 " mem_rdata [31:0] $end
$var wire 1 # mem_rbusy $end
$var wire 1 $ PWRITE $end
$var wire 32 % PWDATA [31:0] $end
$var wire 1 & PSEL $end
$var wire 1 ' PENABLE $end
$var wire 32 ( PADDR [31:0] $end
$var reg 32 ) PRDATA [31:0] $end
$var reg 1 * PREADY $end
$var reg 1 + PSLVERR $end
$var reg 1 , bus_sel $end
$var reg 1 - clk $end
$var reg 32 . mem_addr [31:0] $end
$var reg 1 / mem_rstrb $end
$var reg 32 0 mem_wdata [31:0] $end
$var reg 4 1 mem_wmask [3:0] $end
$var reg 1 2 resetn $end
$scope module dut $end
$var wire 32 3 PRDATA [31:0] $end
$var wire 1 * PREADY $end
$var wire 1 + PSLVERR $end
$var wire 1 , bus_sel $end
$var wire 1 - clk $end
$var wire 32 4 mem_addr [31:0] $end
$var wire 1 # mem_rbusy $end
$var wire 1 / mem_rstrb $end
$var wire 1 ! mem_wbusy $end
$var wire 32 5 mem_wdata [31:0] $end
$var wire 4 6 mem_wmask [3:0] $end
$var wire 1 7 read_req $end
$var wire 1 8 request $end
$var wire 1 2 resetn $end
$var wire 1 9 unused_pslverr $end
$var wire 1 : write_req $end
$var parameter 2 ; S_ENABLE $end
$var parameter 2 < S_IDLE $end
$var parameter 2 = S_SETUP $end
$var reg 32 > PADDR [31:0] $end
$var reg 1 ' PENABLE $end
$var reg 1 & PSEL $end
$var reg 32 ? PWDATA [31:0] $end
$var reg 1 $ PWRITE $end
$var reg 32 @ mem_rdata [31:0] $end
$var reg 2 A state [1:0] $end
$var reg 1 B txn_read $end
$var reg 1 C txn_write $end
$upscope $end
$scope task fail $end
$var reg 128 D message [127:0] $end
$upscope $end
$scope task start_read $end
$var reg 32 E addr [31:0] $end
$upscope $end
$scope task start_write $end
$var reg 32 F addr [31:0] $end
$var reg 32 G data [31:0] $end
$upscope $end
$scope task tick $end
$upscope $end
$upscope $end
$enddefinitions $end
$comment Show the parameter values. $end
$dumpall
b1 =
b0 <
b10 ;
$end
#0
$dumpvars
bx G
bx F
bx E
bx D
xC
xB
bx A
bx @
bx ?
bx >
0:
09
08
07
b0 6
b0 5
b0 4
b0 3
02
b0 1
b0 0
0/
b0 .
0-
0,
0+
0*
b0 )
bx (
x'
x&
bx %
x$
x#
bx "
x!
$end
#5000
0!
0#
b0 %
b0 ?
0'
0&
0$
b0 (
b0 >
b0 "
b0 @
0C
0B
b0 A
1-
#10000
0-
#15000
1-
#16000
12
#20000
0-
#25000
1-
#26000
b11001010111111101011101010111110 )
b11001010111111101011101010111110 3
b10010001101000101011001111000 E
#30000
18
1#
17
1/
b10010001101000101011001111000 .
b10010001101000101011001111000 4
1,
0-
#35000
08
b1 A
1B
1&
b10010001101000101011001111000 (
b10010001101000101011001111000 >
1-
#36000
07
0/
#40000
0-
#45000
b10 A
1'
1-
#50000
0-
#55000
1-
#60000
1*
0-
#65000
0#
b0 A
0B
0'
0&
b11001010111111101011101010111110 "
b11001010111111101011101010111110 @
1-
#66000
0*
b11011110101011011011111011101111 G
b10100100 F
#70000
18
1!
1:
b1111 1
b1111 6
b11011110101011011011111011101111 0
b11011110101011011011111011101111 5
b10100100 .
b10100100 4
0-
#75000
08
b1 A
1C
1&
b11011110101011011011111011101111 %
b11011110101011011011111011101111 ?
1$
b10100100 (
b10100100 >
1-
#76000
0:
b0 1
b0 6
#80000
0-
#85000
b10 A
1'
1-
#90000
0-
#95000
1-
#100000
1*
0-
#105000
0!
b0 A
0C
0'
0&
1-
