DO_AN/DO_AN.srcs/sources_1/new/apb_i2c_slave.v
module apb_i2c_slave (
    input  wire        PCLK, PRESETn,
    input  wire [31:0] I2C_PADDR,
    input  wire        I2C_PSEL, I2C_PENABLE, I2C_PWRITE,
    input  wire [31:0] I2C_PWDATA,
    output reg  [31:0] I2C_PRDATA,
    output wire        PREADY,
    // Các chân I2C vật lý kết nối linh hoạt tri-state bên ngoài top wrapper
    output reg         scl_out,
    output reg         sda_out,
    output reg         sda_oe, // 1: FPGA kéo dây SDA, 0: Thả nổi cho cảm biến kéo
    input  wire        sda_in
);
    reg [7:0] i2c_data;
    reg [3:0] i2c_cmd;
    reg        cmd_trigger;
    wire       i2c_busy;
    wire       rx_ack;
    wire cmd_write = I2C_PSEL && I2C_PENABLE && I2C_PWRITE &&
                     (I2C_PADDR[7:0] == 8'h04);
    assign PREADY = !(cmd_write && i2c_busy);

    wire apb_write = I2C_PSEL && I2C_PENABLE && I2C_PWRITE && PREADY;

    // Giao tiếp APB Write
    always @(posedge PCLK or negedge PRESETn) begin
        if (!PRESETn) begin
            i2c_data    <= 8'h0; 
            i2c_cmd     <= 4'h0; 
            cmd_trigger <= 1'b0;
        end else begin
            cmd_trigger <= 1'b0;
            if (apb_write) begin
                if (I2C_PADDR[7:0] == 8'h00) i2c_data <= I2C_PWDATA[7:0];
                if (I2C_PADDR[7:0] == 8'h04) begin 
                    i2c_cmd     <= I2C_PWDATA[3:0]; 
                    cmd_trigger <= 1'b1; 
                end
            end
        end
    end

    // Giao tiếp APB Read
    always @(*) begin
        if (I2C_PSEL && !I2C_PWRITE) begin
            case (I2C_PADDR[7:0])
                8'h00:   I2C_PRDATA = {24'b0, i2c_data};
                8'h08:   I2C_PRDATA = {30'b0, rx_ack, i2c_busy};
                default: I2C_PRDATA = 32'h0;
            endcase
        end else begin
            I2C_PRDATA = 32'h0;
        end
    end

    // ─── LÕI ĐIỀU KHIỂN I2C STATE MACHINE ───
    reg [3:0] state;
    reg [7:0] clk_cnt;
    reg [2:0] bit_idx;
    reg        busy_reg;
    reg        ack_reg;

    assign i2c_busy = busy_reg;
    assign rx_ack   = ack_reg;

    always @(posedge PCLK or negedge PRESETn) begin
        if (!PRESETn) begin
            state    <= 0; 
            scl_out  <= 1; 
            sda_out  <= 1; 
            sda_oe   <= 1; 
            busy_reg <= 0; 
            ack_reg  <= 0; 
            clk_cnt  <= 0; 
            bit_idx  <= 0;
        end else begin
            case (state)
                0: begin // IDLE
                    scl_out  <= 1'b1;
                    sda_out  <= 1'b1;
                    sda_oe   <= 1'b1;
                    if (cmd_trigger) begin
                        busy_reg <= 1'b1;
                        clk_cnt  <= 0;
                        if (i2c_cmd[0])      state <= 1; // Lệnh START
                        else if (i2c_cmd[1]) state <= 3; // Lệnh STOP
                        else if (i2c_cmd[2]) begin bit_idx <= 7; state <= 5; end // Ghi Byte
                    end else begin
                        busy_reg <= 1'b0;
                    end
                end

                // MẠCH ĐIỀU KHIỂN START CONDITION
                1: begin sda_out <= 1'b0; clk_cnt <= clk_cnt + 1; if(clk_cnt == 50) begin clk_cnt <= 0; state <= 2; end end
                2: begin scl_out <= 1'b0; clk_cnt <= clk_cnt + 1; if(clk_cnt == 50) begin clk_cnt <= 0; state <= 0; end end

                // MẠCH ĐIỀU KHIỂN STOP CONDITION
                3: begin sda_out <= 1'b0; scl_out <= 1'b1; clk_cnt <= clk_cnt + 1; if(clk_cnt == 50) begin clk_cnt <= 0; state <= 4; end end
                4: begin sda_out <= 1'b1; clk_cnt <= clk_cnt + 1; if(clk_cnt == 50) begin clk_cnt <= 0; state <= 0; end end

                // MẠCH TRUYỀN DỮ LIỆU (8-BIT) & KIỂM TRA ACK
                5: begin // Đẩy bit dữ liệu ra dây SDA
                    sda_out <= i2c_data[bit_idx];
                    clk_cnt <= clk_cnt + 1;
                    if (clk_cnt == 25) scl_out <= 1'b1;
                    if (clk_cnt == 50) begin
                        scl_out <= 1'b0;
                        clk_cnt <= 0;
                        if (bit_idx > 0) bit_idx <= bit_idx - 1;
                        else state <= 6; // Chuyển sang chu kỳ kiểm tra bit phản hồi ACK
                    end
                end
                
                6: begin // Nhận cờ ACK từ thiết bị ngoại vi ngoài chip
                    sda_oe  <= 1'b0; // Thả chân SDA cho Slave kéo xuống
                    clk_cnt <= clk_cnt + 1;
                    if (clk_cnt == 25) begin scl_out <= 1'b1; ack_reg <= sda_in; end // Lấy mẫu bit ACK
                    if (clk_cnt == 50) begin
                        scl_out <= 1'b0;
                        clk_cnt <= 0;
                        state   <= 0;
                    end
                end
                default: state <= 0;
            endcase
        end
    end
endmodule

DO_AN/DO_AN.srcs/sim_1/new/tb_apb_i2c_slave_unit.v
`timescale 1ns / 1ps
`default_nettype none

module tb_apb_i2c_slave_unit;
   reg clk = 1'b0;
   reg presetn = 1'b0;

   reg  [31:0] I2C_PADDR = 32'h00000000;
   reg         I2C_PSEL = 1'b0;
   reg         I2C_PENABLE = 1'b0;
   reg         I2C_PWRITE = 1'b0;
   reg  [31:0] I2C_PWDATA = 32'h00000000;
   wire [31:0] I2C_PRDATA;
   wire        PREADY;
   wire        scl_out;
   wire        sda_out;
   wire        sda_oe;
   wire        sda_in;
   reg         slave_drive_low = 1'b0;

   always #5 clk = ~clk;

   pullup(sda_in);
   assign sda_in = sda_oe ? sda_out : 1'bz;
   assign sda_in = slave_drive_low ? 1'b0 : 1'bz;

   apb_i2c_slave dut (
      .PCLK(clk),
      .PRESETn(presetn),
      .I2C_PADDR(I2C_PADDR),
      .I2C_PSEL(I2C_PSEL),
      .I2C_PENABLE(I2C_PENABLE),
      .I2C_PWRITE(I2C_PWRITE),
      .I2C_PWDATA(I2C_PWDATA),
      .I2C_PRDATA(I2C_PRDATA),
      .PREADY(PREADY),
      .scl_out(scl_out),
      .sda_out(sda_out),
      .sda_oe(sda_oe),
      .sda_in(sda_in)
   );

   task fail;
      input [127:0] message;
      begin
         $display("FAIL: %0s", message);
         $finish;
      end
   endtask

   task apb_write;
      input [7:0] addr;
      input [7:0] data;
      begin
         @(negedge clk);
         I2C_PADDR   <= {24'h0, addr};
         I2C_PWDATA  <= {24'h0, data};
         I2C_PWRITE  <= 1'b1;
         I2C_PSEL    <= 1'b1;
         I2C_PENABLE <= 1'b0;
         @(posedge clk);
         #1;
         I2C_PENABLE <= 1'b1;
         while (!PREADY) begin
            @(posedge clk);
            #1;
         end
         @(posedge clk);
         #1;
         I2C_PSEL    <= 1'b0;
         I2C_PENABLE <= 1'b0;
         I2C_PWRITE  <= 1'b0;
         I2C_PADDR   <= 32'h00000000;
         I2C_PWDATA  <= 32'h00000000;
      end
   endtask

   task apb_read;
      input [7:0] addr;
      output [31:0] data;
      begin
         @(negedge clk);
         I2C_PADDR   <= {24'h0, addr};
         I2C_PWRITE  <= 1'b0;
         I2C_PSEL    <= 1'b1;
         I2C_PENABLE <= 1'b0;
         @(posedge clk);
         #1;
         I2C_PENABLE <= 1'b1;
         while (!PREADY) begin
            @(posedge clk);
            #1;
         end
         data = I2C_PRDATA;
         @(posedge clk);
         #1;
         I2C_PSEL    <= 1'b0;
         I2C_PENABLE <= 1'b0;
         I2C_PADDR   <= 32'h00000000;
      end
   endtask

   task wait_for_line_low;
      integer n;
      begin
         for (n = 0; n < 80; n = n + 1) begin
            @(posedge clk);
            #1;
            if (sda_in === 1'b0 && scl_out === 1'b1) begin
               disable wait_for_line_low;
            end
         end
         fail("I2C start condition did not drive SDA low while SCL high");
      end
   endtask

   task wait_for_scl_low;
      integer n;
      begin
         for (n = 0; n < 120; n = n + 1) begin
            @(posedge clk);
            #1;
            if (scl_out === 1'b0) begin
               disable wait_for_scl_low;
            end
         end
         fail("I2C start condition did not complete with SCL low");
      end
   endtask

   task wait_for_bus_high;
      integer n;
      begin
         for (n = 0; n < 160; n = n + 1) begin
            @(posedge clk);
            #1;
            if (scl_out === 1'b1 && sda_in === 1'b1) begin
               disable wait_for_bus_high;
            end
         end
         fail("I2C bus did not return high");
      end
   endtask

   task wait_for_ack_window;
      integer n;
      begin
         for (n = 0; n < 600; n = n + 1) begin
            @(posedge clk);
            #1;
            if (sda_oe === 1'b0) begin
               disable wait_for_ack_window;
            end
         end
         fail("I2C ACK phase was not reached");
      end
   endtask

   task check_idle_high;
      begin
         if (scl_out !== 1'b1 || sda_in !== 1'b1) fail("I2C bus should idle high");
      end
   endtask

   initial begin
      $dumpfile("tb_apb_i2c_slave_unit.vcd");
      $dumpvars(0, tb_apb_i2c_slave_unit);

      repeat (4) @(posedge clk);
      presetn <= 1'b1;
      repeat (2) @(posedge clk);

      check_idle_high();

      apb_write(8'h00, 8'hA0);
      apb_write(8'h04, 8'h01);
      wait_for_line_low();
      wait_for_scl_low();
      wait_for_bus_high();

      apb_write(8'h00, 8'hA0);
      apb_write(8'h04, 8'h04);
      wait_for_ack_window();
      slave_drive_low <= 1'b1;
      repeat (30) @(posedge clk);
      slave_drive_low <= 1'b0;
      repeat (80) @(posedge clk);

      begin : status_check
         reg [31:0] status;
         apb_read(8'h08, status);
         if (status[0] !== 1'b0) fail("I2C busy bit should clear after write");
         if (status[1] !== 1'b0) fail("I2C ACK bit should capture low ACK from slave");
      end

      apb_write(8'h04, 8'h02);
      wait_for_line_low();
      wait_for_bus_high();
      check_idle_high();

      $display("PASS: apb_i2c_slave self-check completed");
      $finish;
   end
endmodule

`default_nettype wire

tb_apb_i2c_slave_unit.vcd
$date
	Fri Jul 24 15:40:08 2026
$end
$version
	Icarus Verilog
$end
$timescale
	1ps
$end
$scope module tb_apb_i2c_slave_unit $end
$var wire 1 ! sda_in $end
$var wire 1 " sda_out $end
$var wire 1 # sda_oe $end
$var wire 1 $ scl_out $end
$var wire 1 % PREADY $end
$var wire 32 & I2C_PRDATA [31:0] $end
$var reg 32 ' I2C_PADDR [31:0] $end
$var reg 1 ( I2C_PENABLE $end
$var reg 1 ) I2C_PSEL $end
$var reg 32 * I2C_PWDATA [31:0] $end
$var reg 1 + I2C_PWRITE $end
$var reg 1 , clk $end
$var reg 1 - presetn $end
$var reg 1 . slave_drive_low $end
$scope module dut $end
$var wire 32 / I2C_PADDR [31:0] $end
$var wire 1 ( I2C_PENABLE $end
$var wire 1 ) I2C_PSEL $end
$var wire 32 0 I2C_PWDATA [31:0] $end
$var wire 1 + I2C_PWRITE $end
$var wire 1 , PCLK $end
$var wire 1 - PRESETn $end
$var wire 1 1 apb_write $end
$var wire 1 2 cmd_write $end
$var wire 1 3 i2c_busy $end
$var wire 1 4 rx_ack $end
$var wire 1 ! sda_in $end
$var wire 1 % PREADY $end
$var reg 32 5 I2C_PRDATA [31:0] $end
$var reg 1 6 ack_reg $end
$var reg 3 7 bit_idx [2:0] $end
$var reg 1 3 busy_reg $end
$var reg 8 8 clk_cnt [7:0] $end
$var reg 1 9 cmd_trigger $end
$var reg 4 : i2c_cmd [3:0] $end
$var reg 8 ; i2c_data [7:0] $end
$var reg 1 $ scl_out $end
$var reg 1 # sda_oe $end
$var reg 1 " sda_out $end
$var reg 4 < state [3:0] $end
$upscope $end
$scope begin status_check $end
$var reg 32 = status [31:0] $end
$upscope $end
$scope task apb_read $end
$var reg 8 > addr [7:0] $end
$var reg 32 ? data [31:0] $end
$upscope $end
$scope task apb_write $end
$var reg 8 @ addr [7:0] $end
$var reg 8 A data [7:0] $end
$upscope $end
$scope task check_idle_high $end
$upscope $end
$scope task fail $end
$var reg 128 B message [127:0] $end
$upscope $end
$scope task wait_for_ack_window $end
$var integer 32 C n [31:0] $end
$upscope $end
$scope task wait_for_bus_high $end
$var integer 32 D n [31:0] $end
$upscope $end
$scope task wait_for_line_low $end
$var integer 32 E n [31:0] $end
$upscope $end
$scope task wait_for_scl_low $end
$var integer 32 F n [31:0] $end
$upscope $end
$upscope $end
$enddefinitions $end
$comment Show the parameter values. $end
$dumpall
$end
#0
$dumpvars
bx F
bx E
bx D
bx C
bx B
bx A
bx @
bx ?
bx >
bx =
bx <
bx ;
bx :
x9
bx 8
bx 7
x6
bx 5
x4
x3
02
01
b0 0
b0 /
0.
0-
0,
0+
b0 *
0)
0(
b0 '
bx &
1%
x$
x#
x"
x!
$end
#5000
b0 &
b0 5
1!
09
b0 :
b0 ;
b0 7
b0 8
04
06
03
1#
1"
1$
b0 <
1,
#10000
0,
#15000
1,
#20000
0,
#25000
1,
#30000
0,
#35000
1-
1,
#40000
0,
#45000
1,
#50000
0,
#55000
b10100000 A
b0 @
1,
#60000
1)
1+
b10100000 *
b10100000 0
0,
#65000
1,
#66000
11
1(
#70000
0,
#75000
b10100000 ;
1,
#76000
01
b0 *
b0 0
0+
0(
0)
b1 A
b100 @
#80000
1)
1+
b1 *
b1 0
b100 '
b100 /
0,
#85000
1,
#86000
12
11
1(
#90000
0,
#95000
19
b1 :
1,
#96000
02
01
b0 *
b0 0
b0 '
b0 /
0+
0(
0)
b0 E
#100000
0,
#105000
09
b1 <
13
1,
#106000
b1 E
#110000
0,
#115000
0!
b1 8
0"
1,
#116000
b0 F
#120000
0,
#125000
b10 8
1,
#126000
b1 F
#130000
0,
#135000
b11 8
1,
#136000
b10 F
#140000
0,
#145000
b100 8
1,
#146000
b11 F
#150000
0,
#155000
b101 8
1,
#156000
b100 F
#160000
0,
#165000
b110 8
1,
#166000
b101 F
#170000
0,
#175000
b111 8
1,
#176000
b110 F
#180000
0,
#185000
b1000 8
1,
#186000
b111 F
#190000
0,
#195000
b1001 8
1,
#196000
b1000 F
#200000
0,
#205000
b1010 8
1,
#206000
b1001 F
#210000
0,
#215000
b1011 8
1,
#216000
b1010 F
#220000
0,
#225000
b1100 8
1,
#226000
b1011 F
#230000
0,
#235000
b1101 8
1,
#236000
b1100 F
#240000
0,
#245000
b1110 8
1,
#246000
b1101 F
#250000
0,
#255000
b1111 8
1,
#256000
b1110 F
#260000
0,
#265000
b10000 8
1,
#266000
b1111 F
#270000
0,
#275000
b10001 8
1,
#276000
b10000 F
#280000
0,
#285000
b10010 8
1,
#286000
b10001 F
#290000
0,
#295000
b10011 8
1,
#296000
b10010 F
#300000
0,
#305000
b10100 8
1,
#306000
b10011 F
#310000
0,
#315000
b10101 8
1,
#316000
b10100 F
#320000
0,
#325000
b10110 8
1,
#326000
b10101 F
#330000
0,
#335000
b10111 8
1,
#336000
b10110 F
#340000
0,
#345000
b11000 8
1,
#346000
b10111 F
#350000
0,
#355000
b11001 8
1,
#356000
b11000 F
#360000
0,
#365000
b11010 8
1,
#366000
b11001 F
#370000
0,
#375000
b11011 8
1,
#376000
b11010 F
#380000
0,
#385000
b11100 8
1,
#386000
b11011 F
#390000
0,
#395000
b11101 8
1,
#396000
b11100 F
#400000
0,
#405000
b11110 8
1,
#406000
b11101 F
#410000
0,
#415000
b11111 8
1,
#416000
b11110 F
#420000
0,
#425000
b100000 8
1,
#426000
b11111 F
#430000
0,
#435000
b100001 8
1,
#436000
b100000 F
#440000
0,
#445000
b100010 8
1,
#446000
b100001 F
#450000
0,
#455000
b100011 8
1,
#456000
b100010 F
#460000
0,
#465000
b100100 8
1,
#466000
b100011 F
#470000
0,
#475000
b100101 8
1,
#476000
b100100 F
#480000
0,
#485000
b100110 8
1,
#486000
b100101 F
#490000
0,
#495000
b100111 8
1,
#496000
b100110 F
#500000
0,
#505000
b101000 8
1,
#506000
b100111 F
#510000
0,
#515000
b101001 8
1,
#516000
b101000 F
#520000
0,
#525000
b101010 8
1,
#526000
b101001 F
#530000
0,
#535000
b101011 8
1,
#536000
b101010 F
#540000
0,
#545000
b101100 8
1,
#546000
b101011 F
#550000
0,
#555000
b101101 8
1,
#556000
b101100 F
#560000
0,
#565000
b101110 8
1,
#566000
b101101 F
#570000
0,
#575000
b101111 8
1,
#576000
b101110 F
#580000
0,
#585000
b110000 8
1,
#586000
b101111 F
#590000
0,
#595000
b110001 8
1,
#596000
b110000 F
#600000
0,
#605000
b110010 8
1,
#606000
b110001 F
#610000
0,
#615000
b10 <
b0 8
1,
#616000
b110010 F
#620000
0,
#625000
b1 8
0$
1,
#626000
b0 D
#630000
0,
#635000
b10 8
1,
#636000
b1 D
#640000
0,
#645000
b11 8
1,
#646000
b10 D
#650000
0,
#655000
b100 8
1,
#656000
b11 D
#660000
0,
#665000
b101 8
1,
#666000
b100 D
#670000
0,
#675000
b110 8
1,
#676000
b101 D
#680000
0,
#685000
b111 8
1,
#686000
b110 D
#690000
0,
#695000
b1000 8
1,
#696000
b111 D
#700000
0,
#705000
b1001 8
1,
#706000
b1000 D
#710000
0,
#715000
b1010 8
1,
#716000
b1001 D
#720000
0,
#725000
b1011 8
1,
#726000
b1010 D
#730000
0,
#735000
b1100 8
1,
#736000
b1011 D
#740000
0,
#745000
b1101 8
1,
#746000
b1100 D
#750000
0,
#755000
b1110 8
1,
#756000
b1101 D
#760000
0,
#765000
b1111 8
1,
#766000
b1110 D
#770000
0,
#775000
b10000 8
1,
#776000
b1111 D
#780000
0,
#785000
b10001 8
1,
#786000
b10000 D
#790000
0,
#795000
b10010 8
1,
#796000
b10001 D
#800000
0,
#805000
b10011 8
1,
#806000
b10010 D
#810000
0,
#815000
b10100 8
1,
#816000
b10011 D
#820000
0,
#825000
b10101 8
1,
#826000
b10100 D
#830000
0,
#835000
b10110 8
1,
#836000
b10101 D
#840000
0,
#845000
b10111 8
1,
#846000
b10110 D
#850000
0,
#855000
b11000 8
1,
#856000
b10111 D
#860000
0,
#865000
b11001 8
1,
#866000
b11000 D
#870000
0,
#875000
b11010 8
1,
#876000
b11001 D
#880000
0,
#885000
b11011 8
1,
#886000
b11010 D
#890000
0,
#895000
b11100 8
1,
#896000
b11011 D
#900000
0,
#905000
b11101 8
1,
#906000
b11100 D
#910000
0,
#915000
b11110 8
1,
#916000
b11101 D
#920000
0,
#925000
b11111 8
1,
#926000
b11110 D
#930000
0,
#935000
b100000 8
1,
#936000
b11111 D
#940000
0,
#945000
b100001 8
1,
#946000
b100000 D
#950000
0,
#955000
b100010 8
1,
#956000
b100001 D
#960000
0,
#965000
b100011 8
1,
#966000
b100010 D
#970000
0,
#975000
b100100 8
1,
#976000
b100011 D
#980000
0,
#985000
b100101 8
1,
#986000
b100100 D
#990000
0,
#995000
b100110 8
1,
#996000
b100101 D
#1000000
0,
#1005000
b100111 8
1,
#1006000
b100110 D
#1010000
0,
#1015000
b101000 8
1,
#1016000
b100111 D
#1020000
0,
#1025000
b101001 8
1,
#1026000
b101000 D
#1030000
0,
#1035000
b101010 8
1,
#1036000
b101001 D
#1040000
0,
#1045000
b101011 8
1,
#1046000
b101010 D
#1050000
0,
#1055000
b101100 8
1,
#1056000
b101011 D
#1060000
0,
#1065000
b101101 8
1,
#1066000
b101100 D
#1070000
0,
#1075000
b101110 8
1,
#1076000
b101101 D
#1080000
0,
#1085000
b101111 8
1,
#1086000
b101110 D
#1090000
0,
#1095000
b110000 8
1,
#1096000
b101111 D
#1100000
0,
#1105000
b110001 8
1,
#1106000
b110000 D
#1110000
0,
#1115000
b110010 8
1,
#1116000
b110001 D
#1120000
0,
#1125000
b0 <
b0 8
1,
#1126000
b110010 D
#1130000
0,
#1135000
1!
03
1"
1$
1,
#1136000
b10100000 A
b0 @
#1140000
1)
1+
b10100000 *
b10100000 0
0,
#1145000
1,
#1146000
11
1(
#1150000
0,
#1155000
1,
#1156000
01
b0 *
b0 0
0+
0(
0)
b100 A
b100 @
#1160000
1)
1+
b100 *
b100 0
b100 '
b100 /
0,
#1165000
1,
#1166000
12
11
1(
#1170000
0,
#1175000
19
b100 :
1,
#1176000
02
01
b0 *
b0 0
b0 '
b0 /
0+
0(
0)
b0 C
#1180000
0,
#1185000
09
b101 <
b111 7
13
1,
#1186000
b1 C
#1190000
0,
#1195000
b1 8
1,
#1196000
b10 C
#1200000
0,
#1205000
b10 8
1,
#1206000
b11 C
#1210000
0,
#1215000
b11 8
1,
#1216000
b100 C
#1220000
0,
#1225000
b100 8
1,
#1226000
b101 C
#1230000
0,
#1235000
b101 8
1,
#1236000
b110 C
#1240000
0,
#1245000
b110 8
1,
#1246000
b111 C
#1250000
0,
#1255000
b111 8
1,
#1256000
b1000 C
#1260000
0,
#1265000
b1000 8
1,
#1266000
b1001 C
#1270000
0,
#1275000
b1001 8
1,
#1276000
b1010 C
#1280000
0,
#1285000
b1010 8
1,
#1286000
b1011 C
#1290000
0,
#1295000
b1011 8
1,
#1296000
b1100 C
#1300000
0,
#1305000
b1100 8
1,
#1306000
b1101 C
#1310000
0,
#1315000
b1101 8
1,
#1316000
b1110 C
#1320000
0,
#1325000
b1110 8
1,
#1326000
b1111 C
#1330000
0,
#1335000
b1111 8
1,
#1336000
b10000 C
#1340000
0,
#1345000
b10000 8
1,
#1346000
b10001 C
#1350000
0,
#1355000
b10001 8
1,
#1356000
b10010 C
#1360000
0,
#1365000
b10010 8
1,
#1366000
b10011 C
#1370000
0,
#1375000
b10011 8
1,
#1376000
b10100 C
#1380000
0,
#1385000
b10100 8
1,
#1386000
b10101 C
#1390000
0,
#1395000
b10101 8
1,
#1396000
b10110 C
#1400000
0,
#1405000
b10110 8
1,
#1406000
b10111 C
#1410000
0,
#1415000
b10111 8
1,
#1416000
b11000 C
#1420000
0,
#1425000
b11000 8
1,
#1426000
b11001 C
#1430000
0,
#1435000
b11001 8
1,
#1436000
b11010 C
#1440000
0,
#1445000
b11010 8
1,
#1446000
b11011 C
#1450000
0,
#1455000
b11011 8
1,
#1456000
b11100 C
#1460000
0,
#1465000
b11100 8
1,
#1466000
b11101 C
#1470000
0,
#1475000
b11101 8
1,
#1476000
b11110 C
#1480000
0,
#1485000
b11110 8
1,
#1486000
b11111 C
#1490000
0,
#1495000
b11111 8
1,
#1496000
b100000 C
#1500000
0,
#1505000
b100000 8
1,
#1506000
b100001 C
#1510000
0,
#1515000
b100001 8
1,
#1516000
b100010 C
#1520000
0,
#1525000
b100010 8
1,
#1526000
b100011 C
#1530000
0,
#1535000
b100011 8
1,
#1536000
b100100 C
#1540000
0,
#1545000
b100100 8
1,
#1546000
b100101 C
#1550000
0,
#1555000
b100101 8
1,
#1556000
b100110 C
#1560000
0,
#1565000
b100110 8
1,
#1566000
b100111 C
#1570000
0,
#1575000
b100111 8
1,
#1576000
b101000 C
#1580000
0,
#1585000
b101000 8
1,
#1586000
b101001 C
#1590000
0,
#1595000
b101001 8
1,
#1596000
b101010 C
#1600000
0,
#1605000
b101010 8
1,
#1606000
b101011 C
#1610000
0,
#1615000
b101011 8
1,
#1616000
b101100 C
#1620000
0,
#1625000
b101100 8
1,
#1626000
b101101 C
#1630000
0,
#1635000
b101101 8
1,
#1636000
b101110 C
#1640000
0,
#1645000
b101110 8
1,
#1646000
b101111 C
#1650000
0,
#1655000
b101111 8
1,
#1656000
b110000 C
#1660000
0,
#1665000
b110000 8
1,
#1666000
b110001 C
#1670000
0,
#1675000
b110001 8
1,
#1676000
b110010 C
#1680000
0,
#1685000
b110010 8
1,
#1686000
b110011 C
#1690000
0,
#1695000
b110 7
0$
b0 8
1,
#1696000
b110100 C
#1700000
0,
#1705000
0!
b1 8
0"
1,
#1706000
b110101 C
#1710000
0,
#1715000
b10 8
1,
#1716000
b110110 C
#1720000
0,
#1725000
b11 8
1,
#1726000
b110111 C
#1730000
0,
#1735000
b100 8
1,
#1736000
b111000 C
#1740000
0,
#1745000
b101 8
1,
#1746000
b111001 C
#1750000
0,
#1755000
b110 8
1,
#1756000
b111010 C
#1760000
0,
#1765000
b111 8
1,
#1766000
b111011 C
#1770000
0,
#1775000
b1000 8
1,
#1776000
b111100 C
#1780000
0,
#1785000
b1001 8
1,
#1786000
b111101 C
#1790000
0,
#1795000
b1010 8
1,
#1796000
b111110 C
#1800000
0,
#1805000
b1011 8
1,
#1806000
b111111 C
#1810000
0,
#1815000
b1100 8
1,
#1816000
b1000000 C
#1820000
0,
#1825000
b1101 8
1,
#1826000
b1000001 C
#1830000
0,
#1835000
b1110 8
1,
#1836000
b1000010 C
#1840000
0,
#1845000
b1111 8
1,
#1846000
b1000011 C
#1850000
0,
#1855000
b10000 8
1,
#1856000
b1000100 C
#1860000
0,
#1865000
b10001 8
1,
#1866000
b1000101 C
#1870000
0,
#1875000
b10010 8
1,
#1876000
b1000110 C
#1880000
0,
#1885000
b10011 8
1,
#1886000
b1000111 C
#1890000
0,
#1895000
b10100 8
1,
#1896000
b1001000 C
#1900000
0,
#1905000
b10101 8
1,
#1906000
b1001001 C
#1910000
0,
#1915000
b10110 8
1,
#1916000
b1001010 C
#1920000
0,
#1925000
b10111 8
1,
#1926000
b1001011 C
#1930000
0,
#1935000
b11000 8
1,
#1936000
b1001100 C
#1940000
0,
#1945000
b11001 8
1,
#1946000
b1001101 C
#1950000
0,
#1955000
1$
b11010 8
1,
#1956000
b1001110 C
#1960000
0,
#1965000
b11011 8
1,
#1966000
b1001111 C
#1970000
0,
#1975000
b11100 8
1,
#1976000
b1010000 C
#1980000
0,
#1985000
b11101 8
1,
#1986000
b1010001 C
#1990000
0,
#1995000
b11110 8
1,
#1996000
b1010010 C
#2000000
0,
#2005000
b11111 8
1,
#2006000
b1010011 C
#2010000
0,
#2015000
b100000 8
1,
#2016000
b1010100 C
#2020000
0,
#2025000
b100001 8
1,
#2026000
b1010101 C
#2030000
0,
#2035000
b100010 8
1,
#2036000
b1010110 C
#2040000
0,
#2045000
b100011 8
1,
#2046000
b1010111 C
#2050000
0,
#2055000
b100100 8
1,
#2056000
b1011000 C
#2060000
0,
#2065000
b100101 8
1,
#2066000
b1011001 C
#2070000
0,
#2075000
b100110 8
1,
#2076000
b1011010 C
#2080000
0,
#2085000
b100111 8
1,
#2086000
b1011011 C
#2090000
0,
#2095000
b101000 8
1,
#2096000
b1011100 C
#2100000
0,
#2105000
b101001 8
1,
#2106000
b1011101 C
#2110000
0,
#2115000
b101010 8
1,
#2116000
b1011110 C
#2120000
0,
#2125000
b101011 8
1,
#2126000
b1011111 C
#2130000
0,
#2135000
b101100 8
1,
#2136000
b1100000 C
#2140000
0,
#2145000
b101101 8
1,
#2146000
b1100001 C
#2150000
0,
#2155000
b101110 8
1,
#2156000
b1100010 C
#2160000
0,
#2165000
b101111 8
1,
#2166000
b1100011 C
#2170000
0,
#2175000
b110000 8
1,
#2176000
b1100100 C
#2180000
0,
#2185000
b110001 8
1,
#2186000
b1100101 C
#2190000
0,
#2195000
b110010 8
1,
#2196000
b1100110 C
#2200000
0,
#2205000
b101 7
0$
b0 8
1,
#2206000
b1100111 C
#2210000
0,
#2215000
1!
b1 8
1"
1,
#2216000
b1101000 C
#2220000
0,
#2225000
b10 8
1,
#2226000
b1101001 C
#2230000
0,
#2235000
b11 8
1,
#2236000
b1101010 C
#2240000
0,
#2245000
b100 8
1,
#2246000
b1101011 C
#2250000
0,
#2255000
b101 8
1,
#2256000
b1101100 C
#2260000
0,
#2265000
b110 8
1,
#2266000
b1101101 C
#2270000
0,
#2275000
b111 8
1,
#2276000
b1101110 C
#2280000
0,
#2285000
b1000 8
1,
#2286000
b1101111 C
#2290000
0,
#2295000
b1001 8
1,
#2296000
b1110000 C
#2300000
0,
#2305000
b1010 8
1,
#2306000
b1110001 C
#2310000
0,
#2315000
b1011 8
1,
#2316000
b1110010 C
#2320000
0,
#2325000
b1100 8
1,
#2326000
b1110011 C
#2330000
0,
#2335000
b1101 8
1,
#2336000
b1110100 C
#2340000
0,
#2345000
b1110 8
1,
#2346000
b1110101 C
#2350000
0,
#2355000
b1111 8
1,
#2356000
b1110110 C
#2360000
0,
#2365000
b10000 8
1,
#2366000
b1110111 C
#2370000
0,
#2375000
b10001 8
1,
#2376000
b1111000 C
#2380000
0,
#2385000
b10010 8
1,
#2386000
b1111001 C
#2390000
0,
#2395000
b10011 8
1,
#2396000
b1111010 C
#2400000
0,
#2405000
b10100 8
1,
#2406000
b1111011 C
#2410000
0,
#2415000
b10101 8
1,
#2416000
b1111100 C
#2420000
0,
#2425000
b10110 8
1,
#2426000
b1111101 C
#2430000
0,
#2435000
b10111 8
1,
#2436000
b1111110 C
#2440000
0,
#2445000
b11000 8
1,
#2446000
b1111111 C
#2450000
0,
#2455000
b11001 8
1,
#2456000
b10000000 C
#2460000
0,
#2465000
1$
b11010 8
1,
#2466000
b10000001 C
#2470000
0,
#2475000
b11011 8
1,
#2476000
b10000010 C
#2480000
0,
#2485000
b11100 8
1,
#2486000
b10000011 C
#2490000
0,
#2495000
b11101 8
1,
#2496000
b10000100 C
#2500000
0,
#2505000
b11110 8
1,
#2506000
b10000101 C
#2510000
0,
#2515000
b11111 8
1,
#2516000
b10000110 C
#2520000
0,
#2525000
b100000 8
1,
#2526000
b10000111 C
#2530000
0,
#2535000
b100001 8
1,
#2536000
b10001000 C
#2540000
0,
#2545000
b100010 8
1,
#2546000
b10001001 C
#2550000
0,
#2555000
b100011 8
1,
#2556000
b10001010 C
#2560000
0,
#2565000
b100100 8
1,
#2566000
b10001011 C
#2570000
0,
#2575000
b100101 8
1,
#2576000
b10001100 C
#2580000
0,
#2585000
b100110 8
1,
#2586000
b10001101 C
#2590000
0,
#2595000
b100111 8
1,
#2596000
b10001110 C
#2600000
0,
#2605000
b101000 8
1,
#2606000
b10001111 C
#2610000
0,
#2615000
b101001 8
1,
#2616000
b10010000 C
#2620000
0,
#2625000
b101010 8
1,
#2626000
b10010001 C
#2630000
0,
#2635000
b101011 8
1,
#2636000
b10010010 C
#2640000
0,
#2645000
b101100 8
1,
#2646000
b10010011 C
#2650000
0,
#2655000
b101101 8
1,
#2656000
b10010100 C
#2660000
0,
#2665000
b101110 8
1,
#2666000
b10010101 C
#2670000
0,
#2675000
b101111 8
1,
#2676000
b10010110 C
#2680000
0,
#2685000
b110000 8
1,
#2686000
b10010111 C
#2690000
0,
#2695000
b110001 8
1,
#2696000
b10011000 C
#2700000
0,
