DO_AN/DO_AN.srcs/sources_1/new/apb_i2c_slave.v
module apb_i2c_slave (
    input  wire        PCLK, PRESETn,
    input  wire [31:0] I2C_PADDR,
    input  wire        I2C_PSEL, I2C_PENABLE, I2C_PWRITE,
    input  wire [31:0] I2C_PWDATA,
    output reg  [31:0] I2C_PRDATA,
    output wire        PREADY,
    // Các chân I2C vật lý kết nối linh hoạt tri-state bên ngoài top wrapper
    output reg         scl_out,
    output reg         sda_out,
    output reg         sda_oe, // 1: FPGA kéo dây SDA, 0: Thả nổi cho cảm biến kéo
    input  wire        sda_in
);
    reg [7:0] i2c_data;
    reg [3:0] i2c_cmd;
    reg        cmd_trigger;
    wire       i2c_busy;
    wire       rx_ack;
    wire cmd_write = I2C_PSEL && I2C_PENABLE && I2C_PWRITE &&
                     (I2C_PADDR[7:0] == 8'h04);
    assign PREADY = !(cmd_write && i2c_busy);

    wire apb_write = I2C_PSEL && I2C_PENABLE && I2C_PWRITE && PREADY;

    // Giao tiếp APB Write
    always @(posedge PCLK or negedge PRESETn) begin
        if (!PRESETn) begin
            i2c_data    <= 8'h0; 
            i2c_cmd     <= 4'h0; 
            cmd_trigger <= 1'b0;
        end else begin
            cmd_trigger <= 1'b0;
            if (apb_write) begin
                if (I2C_PADDR[7:0] == 8'h00) i2c_data <= I2C_PWDATA[7:0];
                if (I2C_PADDR[7:0] == 8'h04) begin 
                    i2c_cmd     <= I2C_PWDATA[3:0]; 
                    cmd_trigger <= 1'b1; 
                end
            end
        end
    end

    // Giao tiếp APB Read
    always @(*) begin
        if (I2C_PSEL && !I2C_PWRITE) begin
            case (I2C_PADDR[7:0])
                8'h00:   I2C_PRDATA = {24'b0, i2c_data};
                8'h08:   I2C_PRDATA = {30'b0, rx_ack, i2c_busy};
                default: I2C_PRDATA = 32'h0;
            endcase
        end else begin
            I2C_PRDATA = 32'h0;
        end
    end

    // ─── LÕI ĐIỀU KHIỂN I2C STATE MACHINE ───
    reg [3:0] state;
    reg [7:0] clk_cnt;
    reg [2:0] bit_idx;
    reg        busy_reg;
    reg        ack_reg;

    assign i2c_busy = busy_reg;
    assign rx_ack   = ack_reg;

    always @(posedge PCLK or negedge PRESETn) begin
        if (!PRESETn) begin
            state    <= 0; 
            scl_out  <= 1; 
            sda_out  <= 1; 
            sda_oe   <= 1; 
            busy_reg <= 0; 
            ack_reg  <= 0; 
            clk_cnt  <= 0; 
            bit_idx  <= 0;
        end else begin
            case (state)
                0: begin // IDLE
                    scl_out  <= 1'b1;
                    sda_out  <= 1'b1;
                    sda_oe   <= 1'b1;
                    if (cmd_trigger) begin
                        busy_reg <= 1'b1;
                        clk_cnt  <= 0;
                        if (i2c_cmd[0])      state <= 1; // Lệnh START
                        else if (i2c_cmd[1]) state <= 3; // Lệnh STOP
                        else if (i2c_cmd[2]) begin bit_idx <= 7; state <= 5; end // Ghi Byte
                    end else begin
                        busy_reg <= 1'b0;
                    end
                end

                // MẠCH ĐIỀU KHIỂN START CONDITION
                1: begin sda_out <= 1'b0; clk_cnt <= clk_cnt + 1; if(clk_cnt == 50) begin clk_cnt <= 0; state <= 2; end end
                2: begin scl_out <= 1'b0; clk_cnt <= clk_cnt + 1; if(clk_cnt == 50) begin clk_cnt <= 0; state <= 0; end end

                // MẠCH ĐIỀU KHIỂN STOP CONDITION
                3: begin sda_out <= 1'b0; scl_out <= 1'b1; clk_cnt <= clk_cnt + 1; if(clk_cnt == 50) begin clk_cnt <= 0; state <= 4; end end
                4: begin sda_out <= 1'b1; clk_cnt <= clk_cnt + 1; if(clk_cnt == 50) begin clk_cnt <= 0; state <= 0; end end

                // MẠCH TRUYỀN DỮ LIỆU (8-BIT) & KIỂM TRA ACK
                5: begin // Đẩy bit dữ liệu ra dây SDA
                    sda_out <= i2c_data[bit_idx];
                    clk_cnt <= clk_cnt + 1;
                    if (clk_cnt == 25) scl_out <= 1'b1;
                    if (clk_cnt == 50) begin
                        scl_out <= 1'b0;
                        clk_cnt <= 0;
                        if (bit_idx > 0) bit_idx <= bit_idx - 1;
                        else state <= 6; // Chuyển sang chu kỳ kiểm tra bit phản hồi ACK
                    end
                end
                
                6: begin // Nhận cờ ACK từ thiết bị ngoại vi ngoài chip
                    sda_oe  <= 1'b0; // Thả chân SDA cho Slave kéo xuống
                    clk_cnt <= clk_cnt + 1;
                    if (clk_cnt == 25) begin scl_out <= 1'b1; ack_reg <= sda_in; end // Lấy mẫu bit ACK
                    if (clk_cnt == 50) begin
                        scl_out <= 1'b0;
                        clk_cnt <= 0;
                        state   <= 0;
                    end
                end
                default: state <= 0;
            endcase
        end
    end
endmodule

DO_AN/DO_AN.srcs/sources_1/new/apb_spi_slave.v
module apb_spi_slave (
    input  wire        PCLK, PRESETn,
    input  wire [31:0] SPI_PADDR,
    input  wire        SPI_PSEL, SPI_PENABLE, SPI_PWRITE,
    input  wire [31:0] SPI_PWDATA,
    output reg  [31:0] SPI_PRDATA,
    output wire        PREADY,
    // Chân vật lý SPI nối cảm biến
    output reg         spi_sclk,
    output reg         spi_cs,
    output wire        spi_mosi,
    input  wire        spi_miso
);
    reg [7:0] tx_shifter;
    reg [7:0] tx_data_buf;
    reg [7:0] rx_data_buf;
    reg       spi_busy;
    reg       start_tx;
    
    assign spi_mosi = tx_shifter[7];
    wire data_write = SPI_PSEL && SPI_PENABLE && SPI_PWRITE &&
                      (SPI_PADDR[7:0] == 8'h00);
    assign PREADY = !(data_write && spi_busy);

    wire apb_write = SPI_PSEL && SPI_PENABLE && SPI_PWRITE && PREADY;

    // Giao tiếp ghi thanh ghi APB
    always @(posedge PCLK or negedge PRESETn) begin
        if (!PRESETn) begin
            spi_cs   <= 1'b1; // Mặc định không chọn chip
            start_tx <= 1'b0;
            tx_data_buf <= 8'h0;
        end else begin
            start_tx <= 1'b0;
            if (apb_write) begin
                case (SPI_PADDR[7:0])
                    8'h00: begin tx_data_buf <= SPI_PWDATA[7:0]; start_tx <= 1'b1; end
                    8'h04: spi_cs <= SPI_PWDATA[0];
                    default: ;
                endcase
            end
        end
    end

    // Giao tiếp đọc thanh ghi APB
    always @(*) begin
        if (SPI_PSEL && !SPI_PWRITE) begin
            case (SPI_PADDR[7:0])
                8'h00:   SPI_PRDATA = {24'b0, rx_data_buf};
                8'h04:  SPI_PRDATA = {31'b0, spi_cs};
                8'h08:   SPI_PRDATA = {31'b0, spi_busy};
                default: SPI_PRDATA = 32'h0;
            endcase
        end else SPI_PRDATA = 32'h0;
    end

    // ─── LÕI ĐIỀU KHIỂN SPI MASTER FSM ───
    reg [2:0] state;
    reg [3:0] bit_cnt;
    reg [7:0] clk_div; // Bộ chia tần số xung SCLK

    always @(posedge PCLK or negedge PRESETn) begin
        if (!PRESETn) begin
            state <= 0; spi_sclk <= 0; bit_cnt <= 0; clk_div <= 0; spi_busy <= 0; rx_data_buf <= 0; tx_shifter <= 0;
        end else begin
            case (state)
                0: begin // IDLE
                    spi_sclk <= 1'b0;
                    if (start_tx && !spi_cs) begin
                        spi_busy <= 1'b1;
                        bit_cnt  <= 0;
                        clk_div  <= 0;
                        tx_shifter <= tx_data_buf;
                        state    <= 1;
                    end else spi_busy <= 1'b0;
                end
                1: begin // Cạnh lên SCLK - Lấy mẫu dữ liệu MISO
                    spi_sclk <= 1'b1;
                    if (clk_div == 8'd5) begin // Điều chỉnh tốc độ truyền SPI
                        clk_div     <= 0;
                        rx_data_buf <= {rx_data_buf[6:0], spi_miso};
                        state       <= 2;
                    end else clk_div <= clk_div + 1;
                end
                2: begin // Cạnh xuống SCLK - Đẩy dữ liệu MOSI mới ra ngoài
                    spi_sclk <= 1'b0;
                    if (clk_div == 8'd5) begin
                        clk_div <= 0;
                        if (bit_cnt < 7) begin
                            bit_cnt    <= bit_cnt + 1;
                            tx_shifter <= tx_shifter << 1;
                            state      <= 1;
                        end else begin
                            state <= 0; // Đã truyền nhận xong 8-bit
                        end
                    end else clk_div <= clk_div + 1;
                end
                default: state <= 0;
            endcase
        end
    end
endmodule

DO_AN/DO_AN.srcs/sources_1/new/apb_uart_slave.v
module apb_uart_slave #(
    parameter CLK_FREQ  = 50000000, // Tần số PCLK mặc định là 50MHz
    parameter BAUD_RATE = 115200
)(
    input  wire        PCLK, PRESETn,
    input  wire [31:0] UART_PADDR,
    input  wire        UART_PSEL, UART_PENABLE, UART_PWRITE,
    input  wire [31:0] UART_PWDATA,
    output reg  [31:0] UART_PRDATA,
    output wire        UART_PREADY,
    // Chân FPGA
    output wire        uart_tx,
    input  wire        uart_rx
);
    // Định nghĩa các thanh ghi nội bộ
    reg [7:0] tx_data;
    reg       tx_start;
    wire      tx_busy;
    wire [7:0] rx_data;
    wire       rx_ready;
    reg        rx_clear;

    // Bộ giải mã địa chỉ APB (Write)
    wire tx_write = UART_PSEL && UART_PENABLE && UART_PWRITE &&
                    (UART_PADDR[7:0] == 8'h00);
    assign UART_PREADY = !(tx_write && tx_busy);

    wire apb_write = UART_PSEL && UART_PENABLE && UART_PWRITE && UART_PREADY;
    always @(posedge PCLK or negedge PRESETn) begin
        if (!PRESETn) begin
            tx_data  <= 8'h0;
            tx_start <= 1'b0;
        end else begin
            tx_start <= 1'b0;
            if (apb_write && (UART_PADDR[7:0] == 8'h00)) begin
                tx_data  <= UART_PWDATA[7:0];
                tx_start <= 1'b1;
            end
        end
    end

    // Bộ giải mã địa chỉ APB (Read)
    wire apb_read = UART_PSEL && !UART_PWRITE;
    always @(*) begin
        rx_clear = 1'b0;
        if (apb_read) begin
            case (UART_PADDR[7:0])
                8'h04: begin
                    UART_PRDATA   = {24'b0, rx_data};
                    rx_clear = UART_PENABLE; // Xóa cờ báo dữ liệu sau khi đọc xong
                end
                8'h08:   UART_PRDATA = {30'b0, rx_ready, !tx_busy};
                default: UART_PRDATA = 32'h0;
            endcase
        end else begin
            UART_PRDATA = 32'h0;
        end
    end

    // ─── LÕI UART TX (PHÁT TÍN HIỆU) ───
    localparam BIT_PERIOD = CLK_FREQ / BAUD_RATE;
    reg [15:0] clk_cnt;
    reg [3:0]  bit_idx;
    reg [9:0]  tx_shift_reg;
    reg        tx_active;

    assign uart_tx = tx_active ? tx_shift_reg[0] : 1'b1;
    assign tx_busy = tx_active || tx_start;

    always @(posedge PCLK or negedge PRESETn) begin
        if (!PRESETn) begin
            clk_cnt <= 0; bit_idx <= 0; tx_active <= 0; tx_shift_reg <= 10'b1;
        end else if (tx_start && !tx_active) begin
            tx_active    <= 1'b1;
            tx_shift_reg <= {1'b1, tx_data, 1'b0}; // [Stop bit (1), Data (8-bit), Start bit (0)]
            clk_cnt      <= 0; bit_idx <= 0;
        end else if (tx_active) begin
            if (clk_cnt < BIT_PERIOD - 1) begin
                clk_cnt <= clk_cnt + 1;
            end else begin
                clk_cnt <= 0;
                if (bit_idx < 9) begin
                    bit_idx      <= bit_idx + 1;
                    tx_shift_reg <= tx_shift_reg >> 1;
                end else begin
                    tx_active <= 1'b0;
                end
            end
        end
    end

    // ─── LÕI UART RX (NHẬN TÍN HIỆU) ───
    // Tự động lấy mẫu ở giữa chu kỳ bit để tránh nhiễu tín hiệu
    reg [1:0] rx_sync;
    always @(posedge PCLK) rx_sync <= {rx_sync[0], uart_rx}; // Chống hiện tượng bất ổn định (Metastability)

    reg        rx_active;
    reg [15:0] rx_clk_cnt;
    reg [3:0]  rx_bit_idx;
    reg [7:0]  rx_shift_data;
    reg        rx_done;

    assign rx_data  = rx_shift_data;
    assign rx_ready = rx_done;

    always @(posedge PCLK or negedge PRESETn) begin
        if (!PRESETn) begin
            rx_active <= 0; rx_clk_cnt <= 0; rx_bit_idx <= 0; rx_done <= 0;
        end else begin
            if (rx_clear) rx_done <= 1'b0;
            
            if (!rx_active && (rx_sync[1] == 1'b0)) begin // Phát hiện Start bit
                rx_active  <= 1'b1;
                rx_clk_cnt <= 0;
                rx_bit_idx <= 0;
            end else if (rx_active) begin
                if (rx_clk_cnt < BIT_PERIOD - 1) begin
                    rx_clk_cnt <= rx_clk_cnt + 1;
                end else begin
                    rx_clk_cnt <= 0;
                    if (rx_bit_idx == 0) begin // Bỏ qua Start bit
                        rx_bit_idx <= rx_bit_idx + 1;
                    end else if (rx_bit_idx <= 8) begin
                        rx_shift_data <= {rx_sync[1], rx_shift_data[7:1]};
                        rx_bit_idx    <= rx_bit_idx + 1;
                    end else begin
                        rx_active <= 1'b0;
                        rx_done   <= 1'b1; // Đã nhận đủ 1 khung byte dữ liệu
                    end
                end
            end
        end
    end
endmodule

DO_AN/DO_AN.srcs/sources_1/new/apb_top.v
// ============================================================
//  SOC APB Top-level
//  Ket noi truc tiep voi 3 module goc:
//    - apb_uart_slave  (apb_uart_slave.v)
//    - apb_spi_slave   (apb_spi_slave.v)
//    - apb_i2c_slave   (apb_i2c_slave.v)
//
//  Memory map:
//    0x4000_0000 - 0x4000_0FFF  UART
//    0x4000_1000 - 0x4000_1FFF  SPI
//    0x4000_2000 - 0x4000_2FFF  I2C
// ============================================================

module apb_top #(
    parameter CLK_FREQ  = 50_000_000,
    parameter BAUD_RATE = 115200
)(
    input  wire        clk,
    input  wire        rst_n,

    // APB master (tu picorv32_apb_bridge)
    input  wire [31:0] PADDR,
    input  wire        PSEL,
    input  wire        PWRITE,
    input  wire        PENABLE,
    input  wire [31:0] PWDATA,
    output reg  [31:0] PRDATA,
    output wire        PREADY,
    output wire        PSLVERR,

    // ── UART ──
    output wire        uart_tx,
    input  wire        uart_rx,
    // (apb_uart_slave khong co IRQ port, khong khai bao)

    // ── SPI ──
    output wire        spi_sclk,   // ten goc: spi_sclk
    output wire        spi_mosi,
    input  wire        spi_miso,
    output wire        spi_cs,     // 1-bit, ten goc: spi_cs

    // ── I2C ──
    output wire        scl_out,    // ten goc: scl_out
    output wire        sda_out,    // ten goc: sda_out
    output wire        sda_oe,
    input  wire        sda_in      // ten goc: sda_in
    // (apb_i2c_slave khong co scl_in, FPGA la master nen chi drive SCL)
);

    // --------------------------------------------------------
    // APB Decoder - sinh PSEL cho tung slave
    // --------------------------------------------------------
    wire psel_uart = PSEL && (PADDR[31:12] == 20'h40000);
    wire psel_spi  = PSEL && (PADDR[31:12] == 20'h40001);
    wire psel_i2c  = PSEL && (PADDR[31:12] == 20'h40002);

    // --------------------------------------------------------
    // PRDATA mux
    // --------------------------------------------------------
    wire [31:0] prdata_uart, prdata_spi, prdata_i2c;
    wire        pready_uart, pready_spi, pready_i2c;

    always @(*) begin
        case (1'b1)
            psel_uart: PRDATA = prdata_uart;
            psel_spi:  PRDATA = prdata_spi;
            psel_i2c:  PRDATA = prdata_i2c;
            default:   PRDATA = 32'h0;
        endcase
    end

    assign PREADY  = psel_uart ? pready_uart :
                     psel_spi  ? pready_spi  :
                     psel_i2c  ? pready_i2c  : 1'b1;
    assign PSLVERR = 1'b0;

    // --------------------------------------------------------
    // UART - apb_uart_slave
    //   Port goc: UART_PADDR, UART_PSEL, UART_PENABLE, UART_PWRITE,
    //             UART_PWDATA, UART_PRDATA, UART_PREADY (= PREADY)
    // --------------------------------------------------------
    apb_uart_slave #(
        .CLK_FREQ  (CLK_FREQ),
        .BAUD_RATE (BAUD_RATE)
    ) u_uart (
        .PCLK        (clk),
        .PRESETn     (rst_n),
        .UART_PADDR  ({24'h0, PADDR[7:0]}),   // chi dung 8-bit offset
        .UART_PSEL   (psel_uart),
        .UART_PENABLE(PENABLE),
        .UART_PWRITE (PWRITE),
        .UART_PWDATA (PWDATA),
        .UART_PRDATA (prdata_uart),
        .UART_PREADY (pready_uart),
        .uart_tx     (uart_tx),
        .uart_rx     (uart_rx)
    );

    // --------------------------------------------------------
    // SPI - apb_spi_slave
    //   Port goc: SPI_PADDR, SPI_PSEL, SPI_PENABLE, SPI_PWRITE,
    //             SPI_PWDATA, SPI_PRDATA, PREADY (= pready_spi)
    //   spi_cs: 1-bit (active low khi =0)
    // --------------------------------------------------------
    apb_spi_slave u_spi (
        .PCLK       (clk),
        .PRESETn    (rst_n),
        .SPI_PADDR  ({24'h0, PADDR[7:0]}),
        .SPI_PSEL   (psel_spi),
        .SPI_PENABLE(PENABLE),
        .SPI_PWRITE (PWRITE),
        .SPI_PWDATA (PWDATA),
        .SPI_PRDATA (prdata_spi),
        .PREADY     (pready_spi),
        .spi_sclk   (spi_sclk),
        .spi_cs     (spi_cs),
        .spi_mosi   (spi_mosi),
        .spi_miso   (spi_miso)
    );

    // --------------------------------------------------------
    // I2C - apb_i2c_slave
    //   Port goc: I2C_PADDR, I2C_PSEL, I2C_PENABLE, I2C_PWRITE,
    //             I2C_PWDATA, I2C_PRDATA, PREADY
    //   scl_out, sda_out, sda_oe, sda_in
    // --------------------------------------------------------
    apb_i2c_slave u_i2c (
        .PCLK       (clk),
        .PRESETn    (rst_n),
        .I2C_PADDR  ({24'h0, PADDR[7:0]}),
        .I2C_PSEL   (psel_i2c),
        .I2C_PENABLE(PENABLE),
        .I2C_PWRITE (PWRITE),
        .I2C_PWDATA (PWDATA),
        .I2C_PRDATA (prdata_i2c),
        .PREADY     (pready_i2c),
        .scl_out    (scl_out),
        .sda_out    (sda_out),
        .sda_oe     (sda_oe),
        .sda_in     (sda_in)
    );

endmodule

DO_AN/DO_AN.srcs/sim_1/new/tb_apb_top_unit.v
`timescale 1ns / 1ps
`default_nettype none

module tb_apb_top_unit;
   localparam [31:0] UART_BASE = 32'h40000000;
   localparam [31:0] SPI_BASE  = 32'h40001000;
   localparam [31:0] I2C_BASE  = 32'h40002000;

   reg clk = 1'b0;
   reg rst_n = 1'b0;

   reg  [31:0] PADDR = 32'h00000000;
   reg         PSEL = 1'b0;
   reg         PWRITE = 1'b0;
   reg         PENABLE = 1'b0;
   reg  [31:0] PWDATA = 32'h00000000;
   wire [31:0] PRDATA;
   wire        PREADY;
   wire        PSLVERR;

   wire uart_tx;
   reg  uart_rx = 1'b1;
   wire spi_sclk;
   wire spi_mosi;
   reg  spi_miso = 1'b1;
   wire spi_cs;
   wire i2c_scl;
   wire i2c_sda_out;
   wire i2c_sda_oe;
   wire i2c_sda;
   reg  i2c_slave_ack_drive_low = 1'b0;

   always #5 clk = ~clk;

   pullup(i2c_sda);
   assign i2c_sda = i2c_sda_oe ? i2c_sda_out : 1'bz;
   assign i2c_sda = i2c_slave_ack_drive_low ? 1'b0 : 1'bz;

   apb_top #(
      .CLK_FREQ(20),
      .BAUD_RATE(10)
   ) dut (
      .clk(clk),
      .rst_n(rst_n),
      .PADDR(PADDR),
      .PSEL(PSEL),
      .PWRITE(PWRITE),
      .PENABLE(PENABLE),
      .PWDATA(PWDATA),
      .PRDATA(PRDATA),
      .PREADY(PREADY),
      .PSLVERR(PSLVERR),
      .uart_tx(uart_tx),
      .uart_rx(uart_rx),
      .spi_sclk(spi_sclk),
      .spi_mosi(spi_mosi),
      .spi_miso(spi_miso),
      .spi_cs(spi_cs),
      .scl_out(i2c_scl),
      .sda_out(i2c_sda_out),
      .sda_oe(i2c_sda_oe),
      .sda_in(i2c_sda)
   );

   task fail;
      input [127:0] message;
      begin
         $display("FAIL: %0s", message);
         $finish;
      end
   endtask

   task apb_read;
      input [31:0] addr;
      output [31:0] data;
      begin
         @(negedge clk);
         PADDR   <= addr;
         PWRITE  <= 1'b0;
         PSEL    <= 1'b1;
         PENABLE <= 1'b0;
         @(posedge clk);
         #1;
         PENABLE <= 1'b1;
         while (!PREADY) begin
            @(posedge clk);
            #1;
         end
         data = PRDATA;
         @(posedge clk);
         #1;
         PSEL    <= 1'b0;
         PENABLE <= 1'b0;
         PADDR   <= 32'h00000000;
      end
   endtask

   initial begin
      $dumpfile("tb_apb_top_unit.vcd");
      $dumpvars(0, tb_apb_top_unit);

      repeat (4) @(posedge clk);
      rst_n <= 1'b1;
      repeat (2) @(posedge clk);

      if (dut.psel_uart !== 1'b0 || dut.psel_spi !== 1'b0 || dut.psel_i2c !== 1'b0) begin
         fail("APB top slaves should be idle after reset");
      end

      begin : uart_check
         reg [31:0] data;
         apb_read(UART_BASE + 32'h08, data);
         if (!dut.psel_uart || dut.psel_spi || dut.psel_i2c) fail("UART decode failed in apb_top");
         if (PREADY !== 1'b1) fail("UART read should be ready in apb_top");
         if (data[1:0] !== 2'b01) fail("UART status mux returned wrong value");
      end

      begin : spi_check
         reg [31:0] data;
         apb_read(SPI_BASE + 32'h08, data);
         if (dut.psel_uart || !dut.psel_spi || dut.psel_i2c) fail("SPI decode failed in apb_top");
         if (data[0] !== 1'b0) fail("SPI status mux returned wrong value");
      end

      begin : i2c_check
         reg [31:0] data;
         apb_read(I2C_BASE + 32'h08, data);
         if (dut.psel_uart || dut.psel_spi || !dut.psel_i2c) fail("I2C decode failed in apb_top");
         if (data[1:0] !== 2'b00) fail("I2C status mux returned wrong value");
      end

      if (PSLVERR !== 1'b0) fail("PSLVERR should be tied low at apb_top");

      $display("PASS: apb_top self-check completed");
      $finish;
   end
endmodule

`default_nettype wire

tb_apb_top_unit.vcd
$date
	Fri Jul 24 15:40:08 2026
$end
$version
	Icarus Verilog
$end
$timescale
	1ps
$end
$scope module tb_apb_top_unit $end
$var wire 1 ! PSLVERR $end
$var wire 1 " i2c_sda $end
$var wire 1 # uart_tx $end
$var wire 1 $ spi_sclk $end
$var wire 1 % spi_mosi $end
$var wire 1 & spi_cs $end
$var wire 1 ' i2c_sda_out $end
$var wire 1 ( i2c_sda_oe $end
$var wire 1 ) i2c_scl $end
$var wire 1 * PREADY $end
$var wire 32 + PRDATA [31:0] $end
$var parameter 32 , I2C_BASE $end
$var parameter 32 - SPI_BASE $end
$var parameter 32 . UART_BASE $end
$var reg 32 / PADDR [31:0] $end
$var reg 1 0 PENABLE $end
$var reg 1 1 PSEL $end
$var reg 32 2 PWDATA [31:0] $end
$var reg 1 3 PWRITE $end
$var reg 1 4 clk $end
$var reg 1 5 i2c_slave_ack_drive_low $end
$var reg 1 6 rst_n $end
$var reg 1 7 spi_miso $end
$var reg 1 8 uart_rx $end
$scope module dut $end
$var wire 32 9 PADDR [31:0] $end
$var wire 1 0 PENABLE $end
$var wire 1 1 PSEL $end
$var wire 1 ! PSLVERR $end
$var wire 32 : PWDATA [31:0] $end
$var wire 1 3 PWRITE $end
$var wire 1 4 clk $end
$var wire 1 ; psel_i2c $end
$var wire 1 < psel_spi $end
$var wire 1 = psel_uart $end
$var wire 1 6 rst_n $end
$var wire 1 " sda_in $end
$var wire 1 7 spi_miso $end
$var wire 1 8 uart_rx $end
$var wire 1 # uart_tx $end
$var wire 1 $ spi_sclk $end
$var wire 1 % spi_mosi $end
$var wire 1 & spi_cs $end
$var wire 1 ' sda_out $end
$var wire 1 ( sda_oe $end
$var wire 1 ) scl_out $end
$var wire 1 > pready_uart $end
$var wire 1 ? pready_spi $end
$var wire 1 @ pready_i2c $end
$var wire 32 A prdata_uart [31:0] $end
$var wire 32 B prdata_spi [31:0] $end
$var wire 32 C prdata_i2c [31:0] $end
$var wire 1 * PREADY $end
$var parameter 32 D BAUD_RATE $end
$var parameter 32 E CLK_FREQ $end
$var reg 32 F PRDATA [31:0] $end
$scope module u_i2c $end
$var wire 32 G I2C_PADDR [31:0] $end
$var wire 1 0 I2C_PENABLE $end
$var wire 1 ; I2C_PSEL $end
$var wire 32 H I2C_PWDATA [31:0] $end
$var wire 1 3 I2C_PWRITE $end
$var wire 1 4 PCLK $end
$var wire 1 6 PRESETn $end
$var wire 1 I apb_write $end
$var wire 1 J cmd_write $end
$var wire 1 K i2c_busy $end
$var wire 1 L rx_ack $end
$var wire 1 " sda_in $end
$var wire 1 @ PREADY $end
$var reg 32 M I2C_PRDATA [31:0] $end
$var reg 1 N ack_reg $end
$var reg 3 O bit_idx [2:0] $end
$var reg 1 K busy_reg $end
$var reg 8 P clk_cnt [7:0] $end
$var reg 1 Q cmd_trigger $end
$var reg 4 R i2c_cmd [3:0] $end
$var reg 8 S i2c_data [7:0] $end
$var reg 1 ) scl_out $end
$var reg 1 ( sda_oe $end
$var reg 1 ' sda_out $end
$var reg 4 T state [3:0] $end
$upscope $end
$scope module u_spi $end
$var wire 1 4 PCLK $end
$var wire 1 6 PRESETn $end
$var wire 32 U SPI_PADDR [31:0] $end
$var wire 1 0 SPI_PENABLE $end
$var wire 1 < SPI_PSEL $end
$var wire 32 V SPI_PWDATA [31:0] $end
$var wire 1 3 SPI_PWRITE $end
$var wire 1 W apb_write $end
$var wire 1 X data_write $end
$var wire 1 7 spi_miso $end
$var wire 1 % spi_mosi $end
$var wire 1 ? PREADY $end
$var reg 32 Y SPI_PRDATA [31:0] $end
$var reg 4 Z bit_cnt [3:0] $end
$var reg 8 [ clk_div [7:0] $end
$var reg 8 \ rx_data_buf [7:0] $end
$var reg 1 ] spi_busy $end
$var reg 1 & spi_cs $end
$var reg 1 $ spi_sclk $end
$var reg 1 ^ start_tx $end
$var reg 3 _ state [2:0] $end
$var reg 8 ` tx_data_buf [7:0] $end
$var reg 8 a tx_shifter [7:0] $end
$upscope $end
$scope module u_uart $end
$var wire 1 4 PCLK $end
$var wire 1 6 PRESETn $end
$var wire 32 b UART_PADDR [31:0] $end
$var wire 1 0 UART_PENABLE $end
$var wire 1 = UART_PSEL $end
$var wire 32 c UART_PWDATA [31:0] $end
$var wire 1 3 UART_PWRITE $end
$var wire 1 d apb_read $end
$var wire 1 e apb_write $end
$var wire 8 f rx_data [7:0] $end
$var wire 1 g rx_ready $end
$var wire 1 h tx_busy $end
$var wire 1 i tx_write $end
$var wire 1 8 uart_rx $end
$var wire 1 # uart_tx $end
$var wire 1 > UART_PREADY $end
$var parameter 32 j BAUD_RATE $end
$var parameter 32 k BIT_PERIOD $end
$var parameter 32 l CLK_FREQ $end
$var reg 32 m UART_PRDATA [31:0] $end
$var reg 4 n bit_idx [3:0] $end
$var reg 16 o clk_cnt [15:0] $end
$var reg 1 p rx_active $end
$var reg 4 q rx_bit_idx [3:0] $end
$var reg 1 r rx_clear $end
$var reg 16 s rx_clk_cnt [15:0] $end
$var reg 1 t rx_done $end
$var reg 8 u rx_shift_data [7:0] $end
$var reg 2 v rx_sync [1:0] $end
$var reg 1 w tx_active $end
$var reg 8 x tx_data [7:0] $end
$var reg 10 y tx_shift_reg [9:0] $end
$var reg 1 z tx_start $end
$upscope $end
$upscope $end
$scope begin i2c_check $end
$var reg 32 { data [31:0] $end
$upscope $end
$scope begin spi_check $end
$var reg 32 | data [31:0] $end
$upscope $end
$scope begin uart_check $end
$var reg 32 } data [31:0] $end
$upscope $end
$scope task apb_read $end
$var reg 32 ~ addr [31:0] $end
$var reg 32 !" data [31:0] $end
$upscope $end
$scope task fail $end
$var reg 128 "" message [127:0] $end
$upscope $end
$upscope $end
$enddefinitions $end
$comment Show the parameter values. $end
$dumpall
b10100 l
b10 k
b1010 j
b10100 E
b1010 D
b1000000000000000000000000000000 .
b1000000000000000001000000000000 -
b1000000000000000010000000000000 ,
$end
#0
$dumpvars
bx ""
bx !"
bx ~
bx }
bx |
bx {
xz
bx y
bx x
xw
bx v
bx u
xt
bx s
0r
bx q
xp
bx o
bx n
b0 m
0i
xh
xg
bx f
0e
0d
b0 c
b0 b
bx a
bx `
bx _
x^
x]
bx \
bx [
bx Z
b0 Y
0X
0W
b0 V
b0 U
bx T
bx S
bx R
xQ
bx P
bx O
xN
b0 M
xL
xK
0J
0I
b0 H
b0 G
b0 F
b0 C
b0 B
b0 A
1@
1?
1>
0=
0<
0;
b0 :
b0 9
18
17
06
05
04
03
b0 2
01
00
b0 /
b0 +
1*
x)
x(
x'
x&
x%
x$
x#
x"
0!
$end
#5000
1#
0h
0%
1"
0z
b0 x
b1 y
0w
b0 n
b0 o
0g
0t
b0 q
b0 s
0p
b0 `
0^
1&
b0 a
b0 \
0]
b0 [
b0 Z
0$
b0 _
0Q
b0 R
b0 S
b0 O
b0 P
0L
0N
0K
1(
1'
1)
b0 T
bx1 v
14
#10000
04
#15000
b11 v
14
#20000
04
#25000
14
#30000
04
#35000
16
14
#40000
04
#45000
14
#50000
04
#55000
b1000000000000000000000000001000 ~
14
#60000
b1 +
b1 F
b1 A
b1 m
1d
1=
b1000 b
b1000 U
b1000 G
11
b1000000000000000000000000001000 /
b1000000000000000000000000001000 9
04
#65000
14
#66000
10
b1 !"
#70000
04
#75000
14
#76000
b0 A
b0 m
0d
b0 +
b0 F
b0 b
b0 U
b0 G
0=
b0 /
b0 9
00
01
b1000000000000000001000000001000 ~
b1 }
#80000
1<
b1000 b
b1000 U
b1000 G
11
b1000000000000000001000000001000 /
b1000000000000000001000000001000 9
04
#85000
14
#86000
10
b0 !"
#90000
04
#95000
14
#96000
b0 b
b0 U
b0 G
0<
b0 /
b0 9
00
01
b1000000000000000010000000001000 ~
b0 |
#100000
1;
b1000 b
b1000 U
b1000 G
11
b1000000000000000010000000001000 /
b1000000000000000010000000001000 9
04
#105000
14
#106000
10
#110000
04
#115000
14
#116000
b0 b
b0 U
b0 G
0;
b0 /
b0 9
00
01
b0 {
