DO_AN/DO_AN.srcs/sources_1/new/apb_spi_slave.v
module apb_spi_slave (
    input  wire        PCLK, PRESETn,
    input  wire [31:0] SPI_PADDR,
    input  wire        SPI_PSEL, SPI_PENABLE, SPI_PWRITE,
    input  wire [31:0] SPI_PWDATA,
    output reg  [31:0] SPI_PRDATA,
    output wire        PREADY,
    // Chân vật lý SPI nối cảm biến
    output reg         spi_sclk,
    output reg         spi_cs,
    output wire        spi_mosi,
    input  wire        spi_miso
);
    reg [7:0] tx_shifter;
    reg [7:0] tx_data_buf;
    reg [7:0] rx_data_buf;
    reg       spi_busy;
    reg       start_tx;
    
    assign spi_mosi = tx_shifter[7];
    wire data_write = SPI_PSEL && SPI_PENABLE && SPI_PWRITE &&
                      (SPI_PADDR[7:0] == 8'h00);
    assign PREADY = !(data_write && spi_busy);

    wire apb_write = SPI_PSEL && SPI_PENABLE && SPI_PWRITE && PREADY;

    // Giao tiếp ghi thanh ghi APB
    always @(posedge PCLK or negedge PRESETn) begin
        if (!PRESETn) begin
            spi_cs   <= 1'b1; // Mặc định không chọn chip
            start_tx <= 1'b0;
            tx_data_buf <= 8'h0;
        end else begin
            start_tx <= 1'b0;
            if (apb_write) begin
                case (SPI_PADDR[7:0])
                    8'h00: begin tx_data_buf <= SPI_PWDATA[7:0]; start_tx <= 1'b1; end
                    8'h04: spi_cs <= SPI_PWDATA[0];
                    default: ;
                endcase
            end
        end
    end

    // Giao tiếp đọc thanh ghi APB
    always @(*) begin
        if (SPI_PSEL && !SPI_PWRITE) begin
            case (SPI_PADDR[7:0])
                8'h00:   SPI_PRDATA = {24'b0, rx_data_buf};
                8'h04:  SPI_PRDATA = {31'b0, spi_cs};
                8'h08:   SPI_PRDATA = {31'b0, spi_busy};
                default: SPI_PRDATA = 32'h0;
            endcase
        end else SPI_PRDATA = 32'h0;
    end

    // ─── LÕI ĐIỀU KHIỂN SPI MASTER FSM ───
    reg [2:0] state;
    reg [3:0] bit_cnt;
    reg [7:0] clk_div; // Bộ chia tần số xung SCLK

    always @(posedge PCLK or negedge PRESETn) begin
        if (!PRESETn) begin
            state <= 0; spi_sclk <= 0; bit_cnt <= 0; clk_div <= 0; spi_busy <= 0; rx_data_buf <= 0; tx_shifter <= 0;
        end else begin
            case (state)
                0: begin // IDLE
                    spi_sclk <= 1'b0;
                    if (start_tx && !spi_cs) begin
                        spi_busy <= 1'b1;
                        bit_cnt  <= 0;
                        clk_div  <= 0;
                        tx_shifter <= tx_data_buf;
                        state    <= 1;
                    end else spi_busy <= 1'b0;
                end
                1: begin // Cạnh lên SCLK - Lấy mẫu dữ liệu MISO
                    spi_sclk <= 1'b1;
                    if (clk_div == 8'd5) begin // Điều chỉnh tốc độ truyền SPI
                        clk_div     <= 0;
                        rx_data_buf <= {rx_data_buf[6:0], spi_miso};
                        state       <= 2;
                    end else clk_div <= clk_div + 1;
                end
                2: begin // Cạnh xuống SCLK - Đẩy dữ liệu MOSI mới ra ngoài
                    spi_sclk <= 1'b0;
                    if (clk_div == 8'd5) begin
                        clk_div <= 0;
                        if (bit_cnt < 7) begin
                            bit_cnt    <= bit_cnt + 1;
                            tx_shifter <= tx_shifter << 1;
                            state      <= 1;
                        end else begin
                            state <= 0; // Đã truyền nhận xong 8-bit
                        end
                    end else clk_div <= clk_div + 1;
                end
                default: state <= 0;
            endcase
        end
    end
endmodule

DO_AN/DO_AN.srcs/sim_1/new/tb_apb_spi_slave_unit.v
`timescale 1ns / 1ps
`default_nettype none

module tb_apb_spi_slave_unit;
   reg clk = 1'b0;
   reg presetn = 1'b0;

   reg  [31:0] SPI_PADDR = 32'h00000000;
   reg         SPI_PSEL = 1'b0;
   reg         SPI_PENABLE = 1'b0;
   reg         SPI_PWRITE = 1'b0;
   reg  [31:0] SPI_PWDATA = 32'h00000000;
   wire [31:0] SPI_PRDATA;
   wire        PREADY;
   wire        spi_sclk;
   wire        spi_cs;
   wire        spi_mosi;
   reg         spi_miso = 1'b1;

   integer sclk_toggle_count = 0;

   always #5 clk = ~clk;

   apb_spi_slave dut (
      .PCLK(clk),
      .PRESETn(presetn),
      .SPI_PADDR(SPI_PADDR),
      .SPI_PSEL(SPI_PSEL),
      .SPI_PENABLE(SPI_PENABLE),
      .SPI_PWRITE(SPI_PWRITE),
      .SPI_PWDATA(SPI_PWDATA),
      .SPI_PRDATA(SPI_PRDATA),
      .PREADY(PREADY),
      .spi_sclk(spi_sclk),
      .spi_cs(spi_cs),
      .spi_mosi(spi_mosi),
      .spi_miso(spi_miso)
   );

   always @(spi_sclk) begin
      if (presetn) begin
         sclk_toggle_count = sclk_toggle_count + 1;
      end
   end

   task fail;
      input [127:0] message;
      begin
         $display("FAIL: %0s", message);
         $finish;
      end
   endtask

   task apb_write;
      input [7:0] addr;
      input [7:0] data;
      begin
         @(negedge clk);
         SPI_PADDR   <= {24'h0, addr};
         SPI_PWDATA  <= {24'h0, data};
         SPI_PWRITE  <= 1'b1;
         SPI_PSEL    <= 1'b1;
         SPI_PENABLE <= 1'b0;
         @(posedge clk);
         #1;
         SPI_PENABLE <= 1'b1;
         while (!PREADY) begin
            @(posedge clk);
            #1;
         end
         @(posedge clk);
         #1;
         SPI_PSEL    <= 1'b0;
         SPI_PENABLE <= 1'b0;
         SPI_PWRITE  <= 1'b0;
         SPI_PADDR   <= 32'h00000000;
         SPI_PWDATA  <= 32'h00000000;
      end
   endtask

   task apb_read;
      input [7:0] addr;
      output [31:0] data;
      begin
         @(negedge clk);
         SPI_PADDR   <= {24'h0, addr};
         SPI_PWRITE  <= 1'b0;
         SPI_PSEL    <= 1'b1;
         SPI_PENABLE <= 1'b0;
         @(posedge clk);
         #1;
         SPI_PENABLE <= 1'b1;
         while (!PREADY) begin
            @(posedge clk);
            #1;
         end
         data = SPI_PRDATA;
         @(posedge clk);
         #1;
         SPI_PSEL    <= 1'b0;
         SPI_PENABLE <= 1'b0;
         SPI_PADDR   <= 32'h00000000;
      end
   endtask

   initial begin
      $dumpfile("tb_apb_spi_slave_unit.vcd");
      $dumpvars(0, tb_apb_spi_slave_unit);

      repeat (4) @(posedge clk);
      presetn <= 1'b1;
      repeat (2) @(posedge clk);

      if (spi_cs !== 1'b1 || spi_sclk !== 1'b0) fail("SPI must idle with CS high and SCLK low");

      apb_write(8'h04, 8'h00);
      if (spi_cs !== 1'b0) fail("SPI CS should go low after CS write");

      sclk_toggle_count = 0;
      spi_miso = 1'b1;
      apb_write(8'h00, 8'hA5);

      repeat (4) @(posedge clk);
      begin : busy_check
         reg [31:0] status;
         apb_read(8'h08, status);
         if (status[0] !== 1'b1) fail("SPI busy bit should be high during transfer");
      end

      repeat (150) @(posedge clk);
      if (sclk_toggle_count < 10) fail("SPI SCLK did not toggle enough during transfer");

      begin : rx_check
         reg [31:0] rx_data;
         apb_read(8'h00, rx_data);
         if (rx_data[7:0] !== 8'hFF) fail("SPI RX data should capture constant MISO=1 as 0xFF");
      end

      begin : done_check
         reg [31:0] status_done;
         apb_read(8'h08, status_done);
         if (status_done[0] !== 1'b0) fail("SPI busy bit should clear after transfer");
      end

      apb_write(8'h04, 8'h01);
      if (spi_cs !== 1'b1) fail("SPI CS should return high after CS write");

      $display("PASS: apb_spi_slave self-check completed");
      $finish;
   end
endmodule

`default_nettype wire

tb_apb_spi_slave_unit.vcd
$date
	Fri Jul 24 15:40:08 2026
$end
$version
	Icarus Verilog
$end
$timescale
	1ps
$end
$scope module tb_apb_spi_slave_unit $end
$var wire 1 ! spi_sclk $end
$var wire 1 " spi_mosi $end
$var wire 1 # spi_cs $end
$var wire 32 $ SPI_PRDATA [31:0] $end
$var wire 1 % PREADY $end
$var reg 32 & SPI_PADDR [31:0] $end
$var reg 1 ' SPI_PENABLE $end
$var reg 1 ( SPI_PSEL $end
$var reg 32 ) SPI_PWDATA [31:0] $end
$var reg 1 * SPI_PWRITE $end
$var reg 1 + clk $end
$var reg 1 , presetn $end
$var reg 1 - spi_miso $end
$var integer 32 . sclk_toggle_count [31:0] $end
$scope module dut $end
$var wire 1 + PCLK $end
$var wire 1 , PRESETn $end
$var wire 32 / SPI_PADDR [31:0] $end
$var wire 1 ' SPI_PENABLE $end
$var wire 1 ( SPI_PSEL $end
$var wire 32 0 SPI_PWDATA [31:0] $end
$var wire 1 * SPI_PWRITE $end
$var wire 1 1 apb_write $end
$var wire 1 2 data_write $end
$var wire 1 - spi_miso $end
$var wire 1 " spi_mosi $end
$var wire 1 % PREADY $end
$var reg 32 3 SPI_PRDATA [31:0] $end
$var reg 4 4 bit_cnt [3:0] $end
$var reg 8 5 clk_div [7:0] $end
$var reg 8 6 rx_data_buf [7:0] $end
$var reg 1 7 spi_busy $end
$var reg 1 # spi_cs $end
$var reg 1 ! spi_sclk $end
$var reg 1 8 start_tx $end
$var reg 3 9 state [2:0] $end
$var reg 8 : tx_data_buf [7:0] $end
$var reg 8 ; tx_shifter [7:0] $end
$upscope $end
$scope begin busy_check $end
$var reg 32 < status [31:0] $end
$upscope $end
$scope begin done_check $end
$var reg 32 = status_done [31:0] $end
$upscope $end
$scope begin rx_check $end
$var reg 32 > rx_data [31:0] $end
$upscope $end
$scope task apb_read $end
$var reg 8 ? addr [7:0] $end
$var reg 32 @ data [31:0] $end
$upscope $end
$scope task apb_write $end
$var reg 8 A addr [7:0] $end
$var reg 8 B data [7:0] $end
$upscope $end
$scope task fail $end
$var reg 128 C message [127:0] $end
$upscope $end
$upscope $end
$enddefinitions $end
$comment Show the parameter values. $end
$dumpall
$end
#0
$dumpvars
bx C
bx B
bx A
bx @
bx ?
bx >
bx =
bx <
bx ;
bx :
bx 9
x8
x7
bx 6
bx 5
bx 4
bx 3
02
01
b0 0
b0 /
b0 .
1-
0,
0+
0*
b0 )
0(
0'
b0 &
1%
bx $
x#
x"
x!
$end
#5000
0"
b0 $
b0 3
b0 :
08
1#
b0 ;
b0 6
07
b0 5
b0 4
0!
b0 9
1+
#10000
0+
#15000
1+
#20000
0+
#25000
1+
#30000
0+
#35000
1,
1+
#40000
0+
#45000
1+
#50000
0+
#55000
b0 B
b100 A
1+
#60000
1(
1*
b100 &
b100 /
0+
#65000
1+
#66000
11
1'
#70000
0+
#75000
0#
1+
#76000
01
b0 &
b0 /
0*
0'
0(
b10100101 B
b0 A
#80000
1(
1*
b10100101 )
b10100101 0
0+
#85000
1+
#86000
12
11
1'
#90000
0+
#95000
18
b10100101 :
1+
#96000
02
01
b0 )
b0 0
0*
0'
0(
#100000
0+
#105000
1"
08
b1 9
b10100101 ;
17
1+
#110000
0+
#115000
b1 .
b1 5
1!
1+
#120000
0+
#125000
b10 5
1+
#130000
0+
#135000
b11 5
b1000 ?
1+
#140000
b1 $
b1 3
1(
b1000 &
b1000 /
0+
#145000
b100 5
1+
#146000
1'
b1 @
#150000
0+
#155000
b101 5
1+
#156000
b0 $
b0 3
b0 &
b0 /
0'
0(
b1 <
#160000
0+
#165000
b10 9
b1 6
b0 5
1+
#170000
0+
#175000
b10 .
b1 5
0!
1+
#180000
0+
#185000
b10 5
1+
#190000
0+
#195000
b11 5
1+
#200000
0+
#205000
b100 5
1+
#210000
0+
#215000
b101 5
1+
#220000
0+
#225000
0"
b1 9
b1001010 ;
b1 4
b0 5
1+
#230000
0+
#235000
b11 .
b1 5
1!
1+
#240000
0+
#245000
b10 5
1+
#250000
0+
#255000
b11 5
1+
#260000
0+
#265000
b100 5
1+
#270000
0+
#275000
b101 5
1+
#280000
0+
#285000
b10 9
b11 6
b0 5
1+
#290000
0+
#295000
b100 .
b1 5
0!
1+
#300000
0+
#305000
b10 5
1+
#310000
0+
#315000
b11 5
1+
#320000
0+
#325000
b100 5
1+
#330000
0+
#335000
b101 5
1+
#340000
0+
#345000
1"
b1 9
b10010100 ;
b10 4
b0 5
1+
#350000
0+
#355000
b101 .
b1 5
1!
1+
#360000
0+
#365000
b10 5
1+
#370000
0+
#375000
b11 5
1+
#380000
0+
#385000
b100 5
1+
#390000
0+
#395000
b101 5
1+
#400000
0+
#405000
b10 9
b111 6
b0 5
1+
#410000
0+
#415000
b110 .
b1 5
0!
1+
#420000
0+
#425000
b10 5
1+
#430000
0+
#435000
b11 5
1+
#440000
0+
#445000
b100 5
1+
#450000
0+
#455000
b101 5
1+
#460000
0+
#465000
0"
b1 9
b101000 ;
b11 4
b0 5
1+
#470000
0+
#475000
b111 .
b1 5
1!
1+
#480000
0+
#485000
b10 5
1+
#490000
0+
#495000
b11 5
1+
#500000
0+
#505000
b100 5
1+
#510000
0+
#515000
b101 5
1+
#520000
0+
#525000
b10 9
b1111 6
b0 5
1+
#530000
0+
#535000
b1000 .
b1 5
0!
1+
#540000
0+
#545000
b10 5
1+
#550000
0+
#555000
b11 5
1+
#560000
0+
#565000
b100 5
1+
#570000
0+
#575000
b101 5
1+
#580000
0+
#585000
b1 9
b1010000 ;
b100 4
b0 5
1+
#590000
0+
#595000
b1001 .
b1 5
1!
1+
#600000
0+
#605000
b10 5
1+
#610000
0+
#615000
b11 5
1+
#620000
0+
#625000
b100 5
1+
#630000
0+
#635000
b101 5
1+
#640000
0+
#645000
b10 9
b11111 6
b0 5
1+
#650000
0+
#655000
b1010 .
b1 5
0!
1+
#660000
0+
#665000
b10 5
1+
#670000
0+
#675000
b11 5
1+
#680000
0+
#685000
b100 5
1+
#690000
0+
#695000
b101 5
1+
#700000
0+
#705000
1"
b1 9
b10100000 ;
b101 4
b0 5
1+
#710000
0+
#715000
b1011 .
b1 5
1!
1+
#720000
0+
#725000
b10 5
1+
#730000
0+
#735000
b11 5
1+
#740000
0+
#745000
b100 5
1+
#750000
0+
#755000
b101 5
1+
#760000
0+
#765000
b10 9
b111111 6
b0 5
1+
#770000
0+
#775000
b1100 .
b1 5
0!
1+
#780000
0+
#785000
b10 5
1+
#790000
0+
#795000
b11 5
1+
#800000
0+
#805000
b100 5
1+
#810000
0+
#815000
b101 5
1+
#820000
0+
#825000
0"
b1 9
b1000000 ;
b110 4
b0 5
1+
#830000
0+
#835000
b1101 .
b1 5
1!
1+
#840000
0+
#845000
b10 5
1+
#850000
0+
#855000
b11 5
1+
#860000
0+
#865000
b100 5
1+
#870000
0+
#875000
b101 5
1+
#880000
0+
#885000
b10 9
b1111111 6
b0 5
1+
#890000
0+
#895000
b1110 .
b1 5
0!
1+
#900000
0+
#905000
b10 5
1+
#910000
0+
#915000
b11 5
1+
#920000
0+
#925000
b100 5
1+
#930000
0+
#935000
b101 5
1+
#940000
0+
#945000
1"
b1 9
b10000000 ;
b111 4
b0 5
1+
#950000
0+
#955000
b1111 .
b1 5
1!
1+
#960000
0+
#965000
b10 5
1+
#970000
0+
#975000
b11 5
1+
#980000
0+
#985000
b100 5
1+
#990000
0+
#995000
b101 5
1+
#1000000
0+
#1005000
b10 9
b11111111 6
b0 5
1+
#1010000
0+
#1015000
b10000 .
b1 5
0!
1+
#1020000
0+
#1025000
b10 5
1+
#1030000
0+
#1035000
b11 5
1+
#1040000
0+
#1045000
b100 5
1+
#1050000
0+
#1055000
b101 5
1+
#1060000
0+
#1065000
b0 9
b0 5
1+
#1070000
0+
#1075000
07
1+
