femtosoc.v
// RAM block extracted from the original FemtoSOC design by Bruno Levy.
// Adapted as a standalone, synthesizable memory for FemtoRV32 Quark.
//
// Quark uses a unified 32-bit instruction/data bus. Reads are synchronous
// (one clock latency), and writes support one byte-enable per data byte.

`default_nettype none

module femto_ram #(
   parameter integer RAM_BYTES = 64 * 1024,
   parameter         INIT_FILE = ""
) (
   input  wire        clk,
   input  wire        ram_sel,

   input  wire [31:0] mem_addr,
   input  wire [31:0] mem_wdata,
   input  wire  [3:0] mem_wmask,
   input  wire        mem_rstrb,

   output reg  [31:0] mem_rdata,
   output wire        mem_rbusy,
   output wire        mem_wbusy
);

   localparam integer RAM_WORDS      = RAM_BYTES / 4;
   localparam integer RAM_ADDR_WIDTH = $clog2(RAM_WORDS);

   wire [RAM_ADDR_WIDTH-1:0] ram_word_addr =
      mem_addr[RAM_ADDR_WIDTH+1:2];

   // Vivado maps this array to 7-series block RAM. The four conditional
   // assignments infer the BRAM byte-write enables used by Quark stores.
   (* ram_style = "block" *)
   reg [31:0] ram [0:RAM_WORDS-1];

   // A synchronous BRAM read already matches Quark's FETCH/WAIT sequencing,
   // so RAM itself does not need to insert additional wait states.
   assign mem_rbusy = 1'b0;
   assign mem_wbusy = 1'b0;

   // Leave INIT_FILE empty when firmware will be loaded by another method.
   // Otherwise pass a Vivado-compatible hexadecimal word file.
   initial begin
      if (INIT_FILE != "") begin
         $readmemh(INIT_FILE, ram);
      end
   end

   always @(posedge clk) begin
      if (ram_sel && mem_rstrb) begin
         mem_rdata <= ram[ram_word_addr];
      end

      if (ram_sel) begin
         if (mem_wmask[0])
            ram[ram_word_addr][7:0]   <= mem_wdata[7:0];
         if (mem_wmask[1])
            ram[ram_word_addr][15:8]  <= mem_wdata[15:8];
         if (mem_wmask[2])
            ram[ram_word_addr][23:16] <= mem_wdata[23:16];
         if (mem_wmask[3])
            ram[ram_word_addr][31:24] <= mem_wdata[31:24];
      end
   end

endmodule

`default_nettype wire

DO_AN/DO_AN.srcs/sim_1/new/tb_femto_ram_unit.v
`timescale 1ns / 1ps
`default_nettype none

module tb_femto_ram_unit;
   localparam integer RAM_BYTES = 64;

   reg clk = 1'b0;
   reg ram_sel = 1'b0;
   reg [31:0] mem_addr = 32'h00000000;
   reg [31:0] mem_wdata = 32'h00000000;
   reg [3:0]  mem_wmask = 4'b0000;
   reg        mem_rstrb = 1'b0;
   wire [31:0] mem_rdata;
   wire        mem_rbusy;
   wire        mem_wbusy;

   integer i;

   always #5 clk = ~clk;

   femto_ram #(
      .RAM_BYTES(RAM_BYTES),
      .INIT_FILE("")
   ) dut (
      .clk(clk),
      .ram_sel(ram_sel),
      .mem_addr(mem_addr),
      .mem_wdata(mem_wdata),
      .mem_wmask(mem_wmask),
      .mem_rstrb(mem_rstrb),
      .mem_rdata(mem_rdata),
      .mem_rbusy(mem_rbusy),
      .mem_wbusy(mem_wbusy)
   );

   task fail;
      input [127:0] message;
      begin
         $display("FAIL: %0s", message);
         $finish;
      end
   endtask

   task write_word;
      input [31:0] addr;
      input [31:0] data;
      input [3:0] mask;
      begin
         @(negedge clk);
         ram_sel   <= 1'b1;
         mem_addr  <= addr;
         mem_wdata <= data;
         mem_wmask <= mask;
         mem_rstrb <= 1'b0;
         @(posedge clk);
         #1;
         mem_wmask <= 4'b0000;
      end
   endtask

   task read_word;
      input [31:0] addr;
      input [31:0] expected;
      begin
         @(negedge clk);
         ram_sel   <= 1'b1;
         mem_addr  <= addr;
         mem_wmask <= 4'b0000;
         mem_rstrb <= 1'b1;
         @(posedge clk);
         #1;
         if (mem_rdata !== expected) begin
            $display("FAIL: read 0x%08h from 0x%08h, expected 0x%08h",
                     mem_rdata, addr, expected);
            $finish;
         end
         mem_rstrb <= 1'b0;
      end
   endtask

   initial begin
      $dumpfile("tb_femto_ram_unit.vcd");
      $dumpvars(0, tb_femto_ram_unit);

      for (i = 0; i < RAM_BYTES / 4; i = i + 1) begin
         dut.ram[i] = 32'h00000000;
      end

      repeat (2) @(posedge clk);

      write_word(32'h00000000, 32'h11223344, 4'b1111);
      read_word(32'h00000000, 32'h11223344);

      write_word(32'h00000000, 32'h0000aa00, 4'b0010);
      read_word(32'h00000000, 32'h1122aa44);

      write_word(32'h00000004, 32'hcc000000, 4'b1000);
      read_word(32'h00000004, 32'hcc000000);

      @(negedge clk);
      ram_sel   <= 1'b0;
      mem_addr  <= 32'h00000008;
      mem_wdata <= 32'hdeadbeef;
      mem_wmask <= 4'b1111;
      @(posedge clk);
      #1;
      if (dut.ram[2] !== 32'h00000000) begin
         fail("write changed memory while ram_sel was low");
      end

      if (mem_rbusy !== 1'b0 || mem_wbusy !== 1'b0) begin
         fail("busy outputs should stay low for femto_ram");
      end

      $display("PASS: femto_ram self-check completed");
      $finish;
   end
endmodule

`default_nettype wire

tb_femto_ram_unit.vcd
$date
	Fri Jul 24 15:40:08 2026
$end
$version
	Icarus Verilog
$end
$timescale
	1ps
$end
$scope module tb_femto_ram_unit $end
$var wire 1 ! mem_rbusy $end
$var wire 1 " mem_wbusy $end
$var wire 32 # mem_rdata [31:0] $end
$var parameter 32 $ RAM_BYTES $end
$var reg 1 % clk $end
$var reg 32 & mem_addr [31:0] $end
$var reg 1 ' mem_rstrb $end
$var reg 32 ( mem_wdata [31:0] $end
$var reg 4 ) mem_wmask [3:0] $end
$var reg 1 * ram_sel $end
$var integer 32 + i [31:0] $end
$scope module dut $end
$var wire 1 % clk $end
$var wire 32 , mem_addr [31:0] $end
$var wire 1 ! mem_rbusy $end
$var wire 1 ' mem_rstrb $end
$var wire 1 " mem_wbusy $end
$var wire 32 - mem_wdata [31:0] $end
$var wire 4 . mem_wmask [3:0] $end
$var wire 1 * ram_sel $end
$var wire 4 / ram_word_addr [3:0] $end
$var parameter 0 0 INIT_FILE $end
$var parameter 32 1 RAM_ADDR_WIDTH $end
$var parameter 32 2 RAM_BYTES $end
$var parameter 32 3 RAM_WORDS $end
$var reg 32 4 mem_rdata [31:0] $end
$upscope $end
$scope task fail $end
$var reg 128 5 message [127:0] $end
$upscope $end
$scope task read_word $end
$var reg 32 6 addr [31:0] $end
$var reg 32 7 expected [31:0] $end
$upscope $end
$scope task write_word $end
$var reg 32 8 addr [31:0] $end
$var reg 32 9 data [31:0] $end
$var reg 4 : mask [3:0] $end
$upscope $end
$upscope $end
$enddefinitions $end
$comment Show the parameter values. $end
$dumpall
b10000 3
b1000000 2
b100 1
b 0
b1000000 $
$end
#0
$dumpvars
bx :
bx 9
bx 8
bx 7
bx 6
bx 5
bx 4
b0 /
b0 .
b0 -
b0 ,
b10000 +
0*
b0 )
b0 (
0'
b0 &
0%
bx #
0"
0!
$end
#5000
1%
#10000
0%
#15000
b1111 :
b10001001000100011001101000100 9
b0 8
1%
#20000
b1111 )
b1111 .
b10001001000100011001101000100 (
b10001001000100011001101000100 -
1*
0%
#25000
1%
#26000
b0 )
b0 .
b10001001000100011001101000100 7
b0 6
#30000
1'
0%
#35000
b10001001000100011001101000100 #
b10001001000100011001101000100 4
1%
#36000
0'
b10 :
b1010101000000000 9
#40000
b10 )
b10 .
b1010101000000000 (
b1010101000000000 -
0%
#45000
1%
#46000
b0 )
b0 .
b10001001000101010101001000100 7
#50000
1'
0%
#55000
b10001001000101010101001000100 #
b10001001000101010101001000100 4
1%
#56000
0'
b1000 :
b11001100000000000000000000000000 9
b100 8
#60000
b1 /
b1000 )
b1000 .
b11001100000000000000000000000000 (
b11001100000000000000000000000000 -
b100 &
b100 ,
0%
#65000
1%
#66000
b0 )
b0 .
b11001100000000000000000000000000 7
b100 6
#70000
1'
0%
#75000
b11001100000000000000000000000000 #
b11001100000000000000000000000000 4
1%
#76000
0'
#80000
b10 /
b1111 )
b1111 .
b11011110101011011011111011101111 (
b11011110101011011011111011101111 -
b1000 &
b1000 ,
0*
0%
